[{"1": {"q1": 1, "q3": 4, "q2": 80, "bb": {"h": null, "startX": 186, "startY": 110, "w": null}, "time": 61}, "2": {"q1": 0, "q3": 4, "q2": 100, "bb": {"h": null, "startX": 263, "startY": 274, "w": null}, "time": 12}, "3": {"q1": 1, "q3": 4, "q2": 100, "bb": {"h": null, "startX": 131, "startY": 202, "w": null}, "time": 26}, "4": {"q1": 1, "q3": 4, "q2": 90, "bb": {"h": null, "startX": 160, "startY": 320, "w": null}, "time": 25}, "5": {"q1": 0, "q3": 4, "q2": 80, "bb": {"h": 1, "startX": 129, "startY": 369, "w": 1}, "time": 23}, "6": {"q1": 1, "q3": 4, "q2": 100, "bb": {"h": null, "startX": 322, "startY": 219, "w": null}, "time": 30}, "7": {"q1": 0, "q3": 4, "q2": 100, "bb": {"h": null, "startX": 45, "startY": 33, "w": null}, "time": 16}, "8": {"q1": 0, "q3": 4, "q2": 100, "bb": {"h": null, "startX": 425, "startY": 311, "w": null}, "time": 17}, "9": {"q1": 0, "q3": 4, "q2": 80, "bb": {"h": null, "startX": 354, "startY": 370, "w": null}, "time": 27}, "10": {"q1": 0, "q3": 4, "q2": 90, "bb": {"h": null, "startX": 228, "startY": 391, "w": null}, "time": 41}, "11": {"q1": 0, "q3": 4, "q2": 90, "bb": {"h": null, "startX": 310, "startY": 359, "w": null}, "time": 46}, "12": {"q1": 1, "q3": 4, "q2": 100, "bb": {"h": null, "startX": 91, "startY": 190, "w": null}, "time": 19}, "13": {"q1": 0, "q3": 3, "q2": 30, "bb": {"h": null, "startX": 254, "startY": 336, "w": null}, "time": 60}, "14": {"q1": 0, "q3": 4, "q2": 100, "bb": {"h": null, "startX": 165, "startY": 457, "w": null}, "time": 49}, "15": {"q1": 0, "q3": 3, "q2": 60, "bb": {"h": -1, "startX": 73, "startY": 315, "w": 0}, "time": 40}, "16": {"q1": 0, "q3": 4, "q2": 80, "bb": {"h": null, "startX": 421, "startY": 291, "w": null}, "time": 10}, "17": {"q1": 1, "q3": 4, "q2": 90, "bb": {"h": null, "startX": 324, "startY": 396, "w": null}, "time": 37}, "18": {"q1": 0, "q3": 4, "q2": 90, "bb": {"h": null, "startX": 178, "startY": 403, "w": null}, "time": 26}, "19": {"q1": 1, "q3": 3, "q2": 80, "bb": {"h": 1, "startX": 363, "startY": 107, "w": 1}, "time": 36}, "20": {"q1": 1, "q3": 3, "q2": 90, "bb": {"h": null, "startX": 400, "startY": 265, "w": null}, "time": 25}, "21": {"q1": 0, "q3": 4, "q2": 80, "bb": {"h": null, "startX": 183, "startY": 262, "w": null}, "time": 22}, "22": {"q1": 0, "q3": 3, "q2": 90, "bb": {"h": null, "startX": 275, "startY": 253, "w": null}, "time": 13}, "23": {"q1": 1, "q3": 3, "q2": 90, "bb": {"h": -1, "startX": 279, "startY": 56, "w": 0}, "time": 61}, "24": {"q1": 0, "q3": 4, "q2": 100, "bb": {"h": -1, "startX": 410, "startY": 271, "w": -1}, "time": 14}, "demographic": {"major": "bachelor ", "estimation": "Yes", "specify": "none", "gender": "Male", "age": "49", "nativeLanguage": "English ", "job": "manager", "nativeSpeaker": "Yes", "employed": "Yes", "education": "2 year degree", "stayInUS": "1 year"}, "name": "A1W0PTQ121819U"}, {"1": {"q1": 0, "q3": 3, "q2": 60, "bb": {"h": 49, "startX": 179, "startY": 291, "w": 11}, "time": 59}, "2": {"q1": 0, "q3": 2, "q2": 80, "bb": {"h": 24, "startX": 15, "startY": 274, "w": 27}, "time": 53}, "3": {"q1": 1, "q3": 2, "q2": 100, "bb": {"h": 117, "startX": 43, "startY": 174, "w": 106}, "time": 33}, "4": {"q1": 1, "q3": 1, "q2": 100, "bb": {"h": 99, "startX": 78, "startY": 280, "w": 137}, "time": 28}, "5": {"q1": 0, "q3": 2, "q2": 20, "bb": {"h": 147, "startX": 418, "startY": 344, "w": 82}, "time": 60}, "6": {"q1": 0, "q3": 3, "q2": 80, "bb": {"h": 36, "startX": 220, "startY": 241, "w": 29}, "time": 53}, "7": {"q1": 0, "q3": 3, "q2": 70, "bb": {"h": 37, "startX": 277, "startY": 436, "w": 18}, "time": 39}, "8": {"q1": 0, "q3": 3, "q2": 90, "bb": {"h": 41, "startX": 14, "startY": 275, "w": 24}, "time": 61}, "9": {"q1": 0, "q3": 3, "q2": 70, "bb": {"h": 27, "startX": 162, "startY": 222, "w": 22}, "time": 60}, "10": {"q1": 0, "q3": 2, "q2": 80, "bb": {"h": 61, "startX": 3, "startY": 248, "w": 14}, "time": 41}, "11": {"q1": 0, "q3": 3, "q2": 80, "bb": {"h": 34, "startX": 119, "startY": 175, "w": 10}, "time": 27}, "12": {"q1": 0, "q3": 2, "q2": 90, "bb": {"h": 28, "startX": 206, "startY": 359, "w": 16}, "time": 36}, "13": {"q1": 0, "q3": 2, "q2": 90, "bb": {"h": 19, "startX": 458, "startY": 176, "w": 14}, "time": 38}, "14": {"q1": 0, "q3": 3, "q2": 70, "bb": {"h": 38, "startX": 297, "startY": 267, "w": 14}, "time": 63}, "15": {"q1": 0, "q3": 3, "q2": 70, "bb": {"h": 12, "startX": 247, "startY": 312, "w": -11}, "time": 47}, "16": {"q1": 0, "q3": 2, "q2": 90, "bb": {"h": 51, "startX": 409, "startY": 276, "w": 19}, "time": 50}, "17": {"q1": 0, "q3": 2, "q2": 60, "bb": {"h": 42, "startX": 91, "startY": 304, "w": 16}, "time": 50}, "18": {"q1": 0, "q3": 2, "q2": 60, "bb": {"h": 67, "startX": 332, "startY": 374, "w": 14}, "time": 44}, "19": {"q1": 0, "q3": 2, "q2": 70, "bb": {"h": 43, "startX": 313, "startY": 298, "w": 19}, "time": 45}, "20": {"q1": 0, "q3": 2, "q2": 70, "bb": {"h": 62, "startX": 457, "startY": 301, "w": 36}, "time": 31}, "21": {"q1": 0, "q3": 2, "q2": 80, "bb": {"h": 43, "startX": 148, "startY": 415, "w": 14}, "time": 60}, "22": {"q1": 0, "q3": 3, "q2": 70, "bb": {"h": -22, "startX": 238, "startY": 280, "w": 23}, "time": 44}, "23": {"q1": 0, "q3": 2, "q2": 70, "bb": {"h": 76, "startX": 434, "startY": 354, "w": 13}, "time": 53}, "24": {"q1": 0, "q3": 3, "q2": 10, "bb": {"h": 138, "startX": 322, "startY": 275, "w": 90}, "time": 60}, "demographic": {"major": "computer science", "estimation": "No", "gender": "Male", "age": "63", "nativeLanguage": "english", "job": "finance", "nativeSpeaker": "Yes", "employed": "Yes", "education": "4 year degree", "stayInUS": "Native (all my life)"}, "name": "A31F1B3F9K311C"}, {"1": {"q1": 0, "q3": 2, "q2": 60, "bb": {"h": 133, "startX": 353, "startY": 501, "w": 63}, "time": 20}, "2": {"q1": 0, "q3": 1, "q2": 70, "bb": {"h": 67, "startX": 360, "startY": 3, "w": 92}, "time": 20}, "3": {"q1": 1, "q3": 2, "q2": 60, "bb": {"h": 73, "startX": 377, "startY": 369, "w": 96}, "time": 38}, "4": {"q1": 1, "q3": 3, "q2": 40, "bb": {"h": 53, "startX": 405, "startY": 448, "w": 63}, "time": 23}, "5": {"q1": 1, "q3": 2, "q2": 40, "bb": {"h": 24, "startX": 128, "startY": 475, "w": 10}, "time": 60}, "6": {"q1": 0, "q3": 2, "q2": 70, "bb": {"h": 92, "startX": 115, "startY": 190, "w": 75}, "time": 18}, "7": {"q1": 0, "q3": 2, "q2": 70, "bb": {"h": 111, "startX": 481, "startY": 158, "w": -47}, "time": 23}, "8": {"q1": 0, "q3": 3, "q2": 70, "bb": {"h": 105, "startX": 132, "startY": 156, "w": 89}, "time": 23}, "9": {"q1": 0, "q3": 3, "q2": 70, "bb": {"h": 69, "startX": 326, "startY": 385, "w": 85}, "time": 21}, "10": {"q1": 0, "q3": 2, "q2": 60, "bb": {"h": 41, "startX": 82, "startY": 294, "w": 70}, "time": 16}, "11": {"q1": 1, "q3": 1, "q2": 80, "bb": {"h": 139, "startX": 391, "startY": 14, "w": 110}, "time": 25}, "12": {"q1": 1, "q3": 2, "q2": 60, "bb": {"h": 106, "startX": 78, "startY": 270, "w": 78}, "time": 20}, "13": {"q1": 0, "q3": 2, "q2": 60, "bb": {"h": 61, "startX": 345, "startY": 214, "w": 112}, "time": 16}, "14": {"q1": 0, "q3": 3, "q2": 60, "bb": {"h": 57, "startX": 28, "startY": 444, "w": 105}, "time": 25}, "15": {"q1": 1, "q3": 2, "q2": 30, "bb": {"h": 286, "startX": 409, "startY": 153, "w": 45}, "time": 20}, "16": {"q1": 0, "q3": 2, "q2": 60, "bb": {"h": 61, "startX": 341, "startY": 8, "w": 142}, "time": 26}, "17": {"q1": 0, "q3": 3, "q2": 60, "bb": {"h": 74, "startX": 190, "startY": 424, "w": 86}, "time": 18}, "18": {"q1": 1, "q3": 2, "q2": 60, "bb": {"h": 73, "startX": 132, "startY": 191, "w": 28}, "time": 19}, "19": {"q1": 1, "q3": 3, "q2": 70, "bb": {"h": 84, "startX": 367, "startY": 286, "w": 53}, "time": 19}, "20": {"q1": 1, "q3": 2, "q2": 70, "bb": {"h": 77, "startX": 177, "startY": 216, "w": 94}, "time": 19}, "21": {"q1": 1, "q3": 2, "q2": 60, "bb": {"h": 49, "startX": 353, "startY": 70, "w": 70}, "time": 60}, "22": {"q1": 1, "q3": 2, "q2": 70, "bb": {"h": 55, "startX": 221, "startY": 321, "w": 81}, "time": 23}, "23": {"q1": 0, "q3": 3, "q2": 40, "bb": {"h": 68, "startX": 412, "startY": 99, "w": 54}, "time": 16}, "24": {"q1": 1, "q3": 2, "q2": 70, "bb": {"h": 96, "startX": 94, "startY": 37, "w": 63}, "time": 19}, "demographic": {"major": "computer", "estimation": "No", "gender": "Female", "age": "25", "job": "HR", "nativeSpeaker": "Yes", "employed": "Yes", "education": "4 year degree", "stayInUS": "Native (all my life)"}, "name": "A1A0NUZBXWJ0XH"}, {"1": {"q1": 0, "q3": 3, "q2": 40, "bb": {"h": 156, "startX": 77, "startY": 218, "w": 156}, "time": 10}, "2": {"q1": 0, "q3": 3, "q2": 50, "bb": {"h": 129, "startX": 183, "startY": 325, "w": 205}, "time": 14}, "3": {"q1": 0, "q3": 3, "q2": 40, "bb": {"h": 196, "startX": 270, "startY": 129, "w": 154}, "time": 12}, "4": {"q1": 1, "q3": 1, "q2": 80, "bb": {"h": 108, "startX": 64, "startY": 274, "w": 175}, "time": 11}, "5": {"q1": 0, "q3": 3, "q2": 40, "bb": {"h": 148, "startX": 284, "startY": 239, "w": 168}, "time": 12}, "6": {"q1": 0, "q3": 3, "q2": 70, "bb": {"h": 136, "startX": 200, "startY": 302, "w": 170}, "time": 14}, "7": {"q1": 0, "q3": 3, "q2": 40, "bb": {"h": 233, "startX": 257, "startY": 161, "w": 141}, "time": 10}, "8": {"q1": 0, "q3": 3, "q2": 70, "bb": {"h": 169, "startX": 211, "startY": 162, "w": 137}, "time": 13}, "9": {"q1": 0, "q3": 3, "q2": 40, "bb": {"h": 137, "startX": 252, "startY": 228, "w": 146}, "time": 14}, "10": {"q1": 0, "q3": 3, "q2": 60, "bb": {"h": 187, "startX": 226, "startY": 248, "w": 165}, "time": 11}, "11": {"q1": 0, "q3": 3, "q2": 30, "bb": {"h": 213, "startX": 290, "startY": 178, "w": 129}, "time": 12}, "12": {"q1": 0, "q3": 3, "q2": 60, "bb": {"h": 174, "startX": 276, "startY": 250, "w": 157}, "time": 14}, "13": {"q1": 0, "q3": 3, "q2": 60, "bb": {"h": 148, "startX": 47, "startY": 195, "w": 160}, "time": 15}, "14": {"q1": 0, "q3": 3, "q2": 70, "bb": {"h": 140, "startX": 112, "startY": 296, "w": 172}, "time": 12}, "15": {"q1": 0, "q3": 3, "q2": 40, "bb": {"h": 196, "startX": 262, "startY": 215, "w": 146}, "time": 12}, "16": {"q1": 0, "q3": 3, "q2": 40, "bb": {"h": 135, "startX": 110, "startY": 265, "w": 192}, "time": 10}, "17": {"q1": 0, "q3": 3, "q2": 40, "bb": {"h": 215, "startX": 209, "startY": 189, "w": 152}, "time": 11}, "18": {"q1": 0, "q3": 3, "q2": 30, "bb": {"h": 192, "startX": 176, "startY": 94, "w": 170}, "time": 12}, "19": {"q1": 0, "q3": 3, "q2": 40, "bb": {"h": 133, "startX": 191, "startY": 365, "w": 173}, "time": 9}, "20": {"q1": 0, "q3": 3, "q2": 40, "bb": {"h": 152, "startX": 203, "startY": 242, "w": 193}, "time": 45}, "21": {"q1": 0, "q3": 3, "q2": 60, "bb": {"h": 158, "startX": 191, "startY": 228, "w": 158}, "time": 12}, "22": {"q1": 0, "q3": 3, "q2": 40, "bb": {"h": 133, "startX": 205, "startY": 206, "w": 182}, "time": 56}, "23": {"q1": 0, "q3": 3, "q2": 40, "bb": {"h": 129, "startX": 141, "startY": 333, "w": 197}, "time": 14}, "24": {"q1": 0, "q3": 2, "q2": 60, "bb": {"h": 146, "startX": 175, "startY": 304, "w": 213}, "time": 21}, "demographic": {"major": "Computer Science", "estimation": "No", "gender": "Female", "age": "26", "job": "Manager", "nativeSpeaker": "Yes", "employed": "Yes", "education": "Master's", "stayInUS": "Native (all my life)"}, "name": "A141SL8P3OXCS0"}, {"1": {"q1": 0, "q3": 4, "q2": 60, "bb": {"h": 98, "startX": 215, "startY": 134, "w": 111}, "time": 15}, "2": {"q1": 0, "q3": 3, "q2": 70, "bb": {"h": 135, "startX": 218, "startY": 195, "w": 128}, "time": 11}, "3": {"q1": 0, "q3": 4, "q2": 70, "bb": {"h": 153, "startX": 244, "startY": 189, "w": 142}, "time": 47}, "4": {"q1": 1, "q3": 2, "q2": 90, "bb": {"h": 72, "startX": 73, "startY": 281, "w": 147}, "time": 34}, "5": {"q1": 0, "q3": 4, "q2": 60, "bb": {"h": 127, "startX": 146, "startY": 139, "w": 114}, "time": 11}, "6": {"q1": 0, "q3": 3, "q2": 60, "bb": {"h": 94, "startX": 224, "startY": 210, "w": 69}, "time": 12}, "7": {"q1": 0, "q3": 4, "q2": 60, "bb": {"h": 52, "startX": 264, "startY": 405, "w": 94}, "time": 21}, "8": {"q1": 1, "q3": 4, "q2": 60, "bb": {"h": 70, "startX": 204, "startY": 4, "w": 113}, "time": 43}, "9": {"q1": 0, "q3": 3, "q2": 60, "bb": {"h": 133, "startX": 104, "startY": 235, "w": 225}, "time": 12}, "10": {"q1": 0, "q3": 4, "q2": 60, "bb": {"h": 146, "startX": 148, "startY": 167, "w": 145}, "time": 10}, "11": {"q1": 1, "q3": 4, "q2": 60, "bb": {"h": 141, "startX": 348, "startY": 24, "w": 132}, "time": 35}, "12": {"q1": 0, "q3": 4, "q2": 60, "bb": {"h": 96, "startX": 307, "startY": 389, "w": 151}, "time": 24}, "13": {"q1": 1, "q3": 4, "q2": 60, "bb": {"h": 104, "startX": 180, "startY": 85, "w": 164}, "time": 20}, "14": {"q1": 1, "q3": 4, "q2": 60, "bb": {"h": 177, "startX": 408, "startY": 54, "w": 90}, "time": 20}, "15": {"q1": 1, "q3": 4, "q2": 60, "bb": {"h": 144, "startX": 25, "startY": 139, "w": 89}, "time": 35}, "16": {"q1": 0, "q3": 4, "q2": 60, "bb": {"h": 81, "startX": 339, "startY": 240, "w": 96}, "time": 11}, "17": {"q1": 0, "q3": 4, "q2": 80, "bb": {"h": 59, "startX": 54, "startY": 280, "w": 101}, "time": 20}, "18": {"q1": 1, "q3": 3, "q2": 70, "bb": {"h": 151, "startX": 300, "startY": 6, "w": 129}, "time": 16}, "19": {"q1": 0, "q3": 4, "q2": 70, "bb": {"h": 114, "startX": 284, "startY": 282, "w": 184}, "time": 10}, "20": {"q1": 0, "q3": 4, "q2": 70, "bb": {"h": 133, "startX": 69, "startY": 97, "w": 161}, "time": 26}, "21": {"q1": 0, "q3": 4, "q2": 70, "bb": {"h": 95, "startX": 132, "startY": 345, "w": 94}, "time": 12}, "22": {"q1": 0, "q3": 3, "q2": 60, "bb": {"h": 106, "startX": 231, "startY": 348, "w": 112}, "time": 11}, "23": {"q1": 0, "q3": 3, "q2": 70, "bb": {"h": 73, "startX": 142, "startY": 310, "w": 98}, "time": 12}, "24": {"q1": 0, "q3": 4, "q2": 70, "bb": {"h": 138, "startX": 379, "startY": 59, "w": 94}, "time": 14}, "demographic": {"major": "n/a", "estimation": "No", "gender": "Male", "age": "35", "nativeLanguage": "English", "job": "Manager", "nativeSpeaker": "Yes", "employed": "Yes", "education": "4 year degree", "stayInUS": "Native (all my life)"}, "name": "A1OB5000KCKNJD"}, {"1": {"q1": 1, "q3": 2, "q2": 40, "bb": {"h": 273, "startX": 5, "startY": 7, "w": 458}, "time": 18}, "2": {"q1": 1, "q3": 2, "q2": 70, "bb": {"h": 427, "startX": 76, "startY": 16, "w": 376}, "time": 17}, "3": {"q1": 1, "q3": 2, "q2": 90, "bb": {"h": 138, "startX": 13, "startY": 159, "w": 137}, "time": 27}, "4": {"q1": 0, "q3": 1, "q2": 90, "bb": {"h": 118, "startX": -1, "startY": 336, "w": 84}, "time": 25}, "5": {"q1": 1, "q3": 3, "q2": 70, "bb": {"h": 411, "startX": 493, "startY": 446, "w": 297}, "time": 22}, "6": {"q1": 1, "q3": 2, "q2": 60, "bb": {"h": 308, "startX": 480, "startY": 310, "w": 489}, "time": 17}, "7": {"q1": 1, "q3": 3, "q2": 80, "bb": {"h": 396, "startX": 491, "startY": 402, "w": 492}, "time": 27}, "8": {"q1": 1, "q3": 3, "q2": 40, "bb": {"h": -355, "startX": 145, "startY": 449, "w": 176}, "time": 61}, "9": {"q1": 1, "q3": 3, "q2": 40, "bb": {"h": 383, "startX": 498, "startY": 500, "w": 233}, "time": 32}, "10": {"q1": 1, "q3": 3, "q2": 70, "bb": {"h": 411, "startX": 473, "startY": 421, "w": 475}, "time": 16}, "11": {"q1": 1, "q3": 3, "q2": 70, "bb": {"h": 464, "startX": 8, "startY": 37, "w": 358}, "time": 26}, "12": {"q1": 1, "q3": 2, "q2": 60, "bb": {"h": 245, "startX": 107, "startY": 214, "w": 357}, "time": 17}, "13": {"q1": 1, "q3": 3, "q2": 60, "bb": {"h": 258, "startX": 21, "startY": 15, "w": 459}, "time": 17}, "14": {"q1": 1, "q3": 2, "q2": 40, "bb": {"h": 259, "startX": 463, "startY": 260, "w": 436}, "time": 25}, "15": {"q1": 1, "q3": 2, "q2": 70, "bb": {"h": 271, "startX": 37, "startY": 107, "w": 334}, "time": 22}, "16": {"q1": 1, "q3": 3, "q2": 40, "bb": {"h": 236, "startX": 98, "startY": 252, "w": 299}, "time": 41}, "17": {"q1": 1, "q3": 2, "q2": 40, "bb": {"h": 347, "startX": 257, "startY": 153, "w": 234}, "time": 18}, "18": {"q1": 1, "q3": 2, "q2": 30, "bb": {"h": 182, "startX": 202, "startY": 34, "w": 283}, "time": 23}, "19": {"q1": 1, "q3": 2, "q2": 40, "bb": {"h": 193, "startX": 252, "startY": 30, "w": 196}, "time": 17}, "20": {"q1": 1, "q3": 2, "q2": 60, "bb": {"h": 281, "startX": 45, "startY": 8, "w": 426}, "time": 13}, "21": {"q1": 1, "q3": 2, "q2": 60, "bb": {"h": 270, "startX": 485, "startY": 291, "w": 444}, "time": 35}, "22": {"q1": 1, "q3": 2, "q2": 60, "bb": {"h": 324, "startX": 23, "startY": 24, "w": 434}, "time": 15}, "23": {"q1": 1, "q3": 2, "q2": 40, "bb": {"h": 171, "startX": 318, "startY": 18, "w": 183}, "time": 38}, "24": {"q1": 1, "q3": 3, "q2": 70, "bb": {"h": 348, "startX": 61, "startY": 6, "w": 399}, "time": 22}, "demographic": {"major": "Computer Science", "estimation": "No", "gender": "Male", "age": "32", "job": "IT - Computer Engineer", "nativeSpeaker": "Yes", "employed": "Yes", "education": "4 year degree", "stayInUS": "Native (all my life)"}, "name": "A173XBIUVI8WAW"}, {"1": {"q1": 1, "q3": 3, "q2": 80, "bb": {"h": 46, "startX": 258, "startY": 329, "w": 115}, "time": 20}, "2": {"q1": 1, "q3": 3, "q2": 60, "bb": {"h": 99, "startX": 171, "startY": 401, "w": 93}, "time": 25}, "3": {"q1": 1, "q3": 3, "q2": 60, "bb": {"h": 124, "startX": 436, "startY": 5, "w": 58}, "time": 35}, "4": {"q1": 0, "q3": 3, "q2": 60, "bb": {"h": 61, "startX": 401, "startY": 437, "w": 62}, "time": 24}, "5": {"q1": 1, "q3": 3, "q2": 70, "bb": {"h": 120, "startX": 178, "startY": 357, "w": 131}, "time": 38}, "6": {"q1": 1, "q3": 3, "q2": 50, "bb": {"h": 104, "startX": 48, "startY": 297, "w": 64}, "time": 22}, "7": {"q1": 1, "q3": 4, "q2": 90, "bb": {"h": 34, "startX": 169, "startY": 462, "w": 112}, "time": 39}, "8": {"q1": 1, "q3": 2, "q2": 70, "bb": {"h": 46, "startX": 230, "startY": 320, "w": 182}, "time": 24}, "9": {"q1": 1, "q3": 3, "q2": 70, "bb": {"h": 101, "startX": 65, "startY": 284, "w": 153}, "time": 14}, "10": {"q1": 1, "q3": 3, "q2": 60, "bb": {"h": 123, "startX": 180, "startY": 93, "w": 79}, "time": 29}, "11": {"q1": 0, "q3": 4, "q2": 80, "bb": {"h": 69, "startX": 289, "startY": 210, "w": 173}, "time": 20}, "12": {"q1": 1, "q3": 2, "q2": 80, "bb": {"h": 64, "startX": 229, "startY": 98, "w": 157}, "time": 16}, "13": {"q1": 1, "q3": 2, "q2": 70, "bb": {"h": 88, "startX": 222, "startY": 299, "w": 163}, "time": 35}, "14": {"q1": 1, "q3": 3, "q2": 90, "bb": {"h": -126, "startX": 306, "startY": 3, "w": -136}, "time": 27}, "15": {"q1": 1, "q3": 2, "q2": 90, "bb": {"h": 94, "startX": 127, "startY": 271, "w": 150}, "time": 14}, "16": {"q1": 1, "q3": 3, "q2": 70, "bb": {"h": -78, "startX": 61, "startY": 102, "w": 128}, "time": 32}, "17": {"q1": 1, "q3": 3, "q2": 80, "bb": {"h": 81, "startX": 178, "startY": 400, "w": 105}, "time": 33}, "18": {"q1": 1, "q3": 2, "q2": 80, "bb": {"h": 122, "startX": 410, "startY": 125, "w": 53}, "time": 21}, "19": {"q1": 1, "q3": 2, "q2": 80, "bb": {"h": 99, "startX": 364, "startY": 199, "w": 99}, "time": 19}, "20": {"q1": 1, "q3": 2, "q2": 80, "bb": {"h": 94, "startX": 144, "startY": 401, "w": 30}, "time": 24}, "21": {"q1": 1, "q3": 3, "q2": 80, "bb": {"h": 128, "startX": 433, "startY": 44, "w": 64}, "time": 32}, "22": {"q1": 1, "q3": 3, "q2": 90, "bb": {"h": -124, "startX": 367, "startY": 480, "w": 44}, "time": 16}, "23": {"q1": 1, "q3": 4, "q2": 80, "bb": {"h": 96, "startX": 27, "startY": 345, "w": 95}, "time": 50}, "24": {"q1": 1, "q3": 3, "q2": 80, "bb": {"h": 75, "startX": 92, "startY": 302, "w": 149}, "time": 32}, "demographic": {"major": "Computer", "estimation": "No", "gender": "Male", "age": "34", "job": "manager", "nativeSpeaker": "Yes", "employed": "Yes", "education": "Master's", "stayInUS": "Native (all my life)"}, "name": "A1K63DWVK9EM69"}, {"1": {"q1": 0, "q3": 4, "q2": 70, "bb": {"h": 241, "startX": 3, "startY": 95, "w": 198}, "time": 55}, "2": {"q1": 0, "q3": 4, "q2": 70, "bb": {"h": 209, "startX": 226, "startY": 285, "w": 271}, "time": 24}, "3": {"q1": 0, "q3": 4, "q2": 70, "bb": {"h": 265, "startX": -1, "startY": 234, "w": 315}, "time": 26}, "4": {"q1": 0, "q3": 4, "q2": 80, "bb": {"h": 187, "startX": 260, "startY": 0, "w": 239}, "time": 28}, "5": {"q1": 0, "q3": 4, "q2": 80, "bb": {"h": 230, "startX": 291, "startY": -1, "w": 204}, "time": 29}, "6": {"q1": 0, "q3": 4, "q2": 70, "bb": {"h": 257, "startX": 3, "startY": 239, "w": 271}, "time": 24}, "7": {"q1": 0, "q3": 4, "q2": 80, "bb": {"h": 196, "startX": 259, "startY": 0, "w": 238}, "time": 24}, "8": {"q1": 0, "q3": 4, "q2": 70, "bb": {"h": 183, "startX": 1, "startY": 0, "w": 284}, "time": 28}, "9": {"q1": 0, "q3": 4, "q2": 80, "bb": {"h": 236, "startX": 321, "startY": 264, "w": 180}, "time": 22}, "10": {"q1": 0, "q3": 3, "q2": 70, "bb": {"h": 253, "startX": 270, "startY": 0, "w": 231}, "time": 24}, "11": {"q1": 0, "q3": 3, "q2": 80, "bb": {"h": 153, "startX": 150, "startY": 317, "w": 204}, "time": 60}, "12": {"q1": 0, "q3": 4, "q2": 80, "bb": {"h": 197, "startX": 279, "startY": 297, "w": 219}, "time": 21}, "13": {"q1": 0, "q3": 4, "q2": 70, "bb": {"h": 270, "startX": 238, "startY": 87, "w": 260}, "time": 22}, "14": {"q1": 0, "q3": 4, "q2": 70, "bb": {"h": 208, "startX": 230, "startY": 1, "w": 265}, "time": 30}, "15": {"q1": 0, "q3": 4, "q2": 70, "bb": {"h": 276, "startX": -2, "startY": 110, "w": 237}, "time": 45}, "16": {"q1": 0, "q3": 4, "q2": 70, "bb": {"h": 251, "startX": 89, "startY": 243, "w": 351}, "time": 61}, "17": {"q1": 0, "q3": 4, "q2": 70, "bb": {"h": 226, "startX": 271, "startY": 267, "w": 230}, "time": 37}, "18": {"q1": 0, "q3": 4, "q2": 80, "bb": {"h": 175, "startX": 216, "startY": -1, "w": 278}, "time": 44}, "19": {"q1": 0, "q3": 4, "q2": 80, "bb": {"h": 210, "startX": 4, "startY": 4, "w": 244}, "time": 28}, "20": {"q1": 0, "q3": 4, "q2": 80, "bb": {"h": 208, "startX": 3, "startY": 0, "w": 326}, "time": 25}, "21": {"q1": 0, "q3": 3, "q2": 70, "bb": {"h": 225, "startX": 1, "startY": -1, "w": 218}, "time": 27}, "22": {"q1": 0, "q3": 4, "q2": 80, "bb": {"h": 215, "startX": 242, "startY": 2, "w": 252}, "time": 32}, "23": {"q1": 0, "q3": 4, "q2": 80, "bb": {"h": 216, "startX": 206, "startY": 279, "w": 290}, "time": 20}, "24": {"q1": 0, "q3": 4, "q2": 70, "bb": {"h": 263, "startX": 231, "startY": 221, "w": 268}, "time": 36}, "demographic": {"major": "English", "estimation": "No", "gender": "Male", "age": "36", "job": "Administrator", "nativeSpeaker": "Yes", "employed": "Yes", "education": "4 year degree", "stayInUS": "Native (all my life)"}, "name": "AGA4AUTR0ADWF"}, {"1": {"q1": 1, "q3": 2, "q2": 50, "bb": {"h": 164, "startX": 332, "startY": 137, "w": 104}, "time": 26}, "2": {"q1": 1, "q3": 2, "q2": 70, "bb": {"h": 103, "startX": 426, "startY": 397, "w": 75}, "time": 22}, "3": {"q1": 1, "q3": 2, "q2": 90, "bb": {"h": 141, "startX": 23, "startY": 154, "w": 126}, "time": 35}, "4": {"q1": 1, "q3": 2, "q2": 100, "bb": {"h": 119, "startX": 74, "startY": 259, "w": 148}, "time": 16}, "5": {"q1": 1, "q3": 2, "q2": 70, "bb": {"h": 136, "startX": 157, "startY": 161, "w": 69}, "time": 15}, "6": {"q1": 1, "q3": 2, "q2": 70, "bb": {"h": 147, "startX": 336, "startY": 237, "w": 165}, "time": 42}, "7": {"q1": 1, "q3": 2, "q2": 60, "bb": {"h": 135, "startX": 295, "startY": 63, "w": 143}, "time": 21}, "8": {"q1": 1, "q3": 2, "q2": 60, "bb": {"h": 175, "startX": 36, "startY": 199, "w": 69}, "time": 14}, "9": {"q1": 1, "q3": 2, "q2": 70, "bb": {"h": 141, "startX": 4, "startY": 4, "w": 124}, "time": 17}, "10": {"q1": 1, "q3": 2, "q2": 60, "bb": {"h": 157, "startX": 272, "startY": 323, "w": 104}, "time": 13}, "11": {"q1": 1, "q3": 2, "q2": 70, "bb": {"h": 138, "startX": 14, "startY": 352, "w": 148}, "time": 21}, "12": {"q1": 1, "q3": 2, "q2": 60, "bb": {"h": 181, "startX": 196, "startY": 214, "w": 132}, "time": 20}, "13": {"q1": 1, "q3": 2, "q2": 60, "bb": {"h": 145, "startX": 22, "startY": 193, "w": 72}, "time": 13}, "14": {"q1": 1, "q3": 2, "q2": 60, "bb": {"h": 126, "startX": 428, "startY": 223, "w": 67}, "time": 20}, "15": {"q1": 1, "q3": 2, "q2": 60, "bb": {"h": 93, "startX": 23, "startY": 8, "w": 94}, "time": 60}, "16": {"q1": 1, "q3": 2, "q2": 70, "bb": {"h": 127, "startX": 111, "startY": 366, "w": 113}, "time": 20}, "17": {"q1": 1, "q3": 2, "q2": 70, "bb": {"h": 123, "startX": 240, "startY": 347, "w": 152}, "time": 18}, "18": {"q1": 1, "q3": 2, "q2": 70, "bb": {"h": 90, "startX": 115, "startY": 155, "w": 89}, "time": 21}, "19": {"q1": 1, "q3": 2, "q2": 70, "bb": {"h": 136, "startX": 276, "startY": 39, "w": 163}, "time": 13}, "20": {"q1": 1, "q3": 2, "q2": 70, "bb": {"h": 61, "startX": 426, "startY": 488, "w": 84}, "time": 19}, "21": {"q1": 1, "q3": 2, "q2": 70, "bb": {"h": 159, "startX": 333, "startY": 271, "w": 137}, "time": 21}, "22": {"q1": 1, "q3": 2, "q2": 80, "bb": {"h": 124, "startX": 214, "startY": 5, "w": 112}, "time": 28}, "23": {"q1": 1, "q3": 2, "q2": 70, "bb": {"h": 139, "startX": 163, "startY": 12, "w": 106}, "time": 20}, "24": {"q1": 1, "q3": 2, "q2": 70, "bb": {"h": 88, "startX": 159, "startY": 379, "w": 157}, "time": 18}, "demographic": {"major": "SOCIOLOGY", "estimation": "No", "gender": "Female", "age": "48", "job": "ACCOUNTANT", "nativeSpeaker": "Yes", "employed": "Yes", "education": "Master's", "stayInUS": "Native (all my life)"}, "name": "A56J5OHML6XX5"}, {"1": {"q1": 1, "q3": 3, "q2": 80, "bb": {"h": 428, "startX": 481, "startY": 435, "w": 423}, "time": 12}, "2": {"q1": 1, "q3": 4, "q2": 70, "bb": {"h": 408, "startX": 488, "startY": 482, "w": 429}, "time": 22}, "3": {"q1": 0, "q3": 3, "q2": 70, "bb": {"h": 383, "startX": 467, "startY": 450, "w": 285}, "time": 60}, "4": {"q1": 1, "q3": 2, "q2": 80, "bb": {"h": 189, "startX": 270, "startY": 422, "w": 211}, "time": 12}, "5": {"q1": 0, "q3": 3, "q2": 80, "bb": {"h": 446, "startX": 343, "startY": 466, "w": 320}, "time": 23}, "6": {"q1": 0, "q3": 3, "q2": 70, "bb": {"h": -239, "startX": 156, "startY": 9, "w": -332}, "time": 22}, "7": {"q1": 1, "q3": 2, "q2": 70, "bb": {"h": 374, "startX": 89, "startY": 34, "w": 280}, "time": 60}, "8": {"q1": 1, "q3": 2, "q2": 70, "bb": {"h": 238, "startX": 290, "startY": 260, "w": 205}, "time": 46}, "9": {"q1": 1, "q3": 3, "q2": 70, "bb": {"h": 357, "startX": 172, "startY": 68, "w": 317}, "time": 8}, "10": {"q1": 1, "q3": 3, "q2": 40, "bb": {"h": 389, "startX": 498, "startY": 400, "w": 254}, "time": 56}, "11": {"q1": 1, "q3": 3, "q2": 70, "bb": {"h": -174, "startX": 21, "startY": 7, "w": -469}, "time": 22}, "12": {"q1": 1, "q3": 4, "q2": 70, "bb": {"h": 314, "startX": 432, "startY": 422, "w": 315}, "time": 19}, "13": {"q1": 0, "q3": 3, "q2": 70, "bb": {"h": 368, "startX": 97, "startY": 36, "w": 380}, "time": 30}, "14": {"q1": 0, "q3": 4, "q2": 70, "bb": {"h": 397, "startX": 374, "startY": 442, "w": 328}, "time": 27}, "15": {"q1": 1, "q3": 3, "q2": 70, "bb": {"h": 463, "startX": 477, "startY": 473, "w": 441}, "time": 11}, "16": {"q1": 0, "q3": 3, "q2": 70, "bb": {"h": 370, "startX": 87, "startY": 127, "w": 313}, "time": 33}, "17": {"q1": 0, "q3": 3, "q2": 70, "bb": {"h": 425, "startX": 490, "startY": 468, "w": 387}, "time": 10}, "18": {"q1": 1, "q3": 3, "q2": 70, "bb": {"h": 274, "startX": 382, "startY": 497, "w": 366}, "time": 33}, "19": {"q1": 1, "q3": 3, "q2": 80, "bb": {"h": 350, "startX": 52, "startY": 103, "w": 372}, "time": 27}, "20": {"q1": 0, "q3": 4, "q2": 80, "bb": {"h": 322, "startX": 496, "startY": 356, "w": 438}, "time": 23}, "21": {"q1": 1, "q3": 2, "q2": 80, "bb": {"h": 357, "startX": 201, "startY": 59, "w": 297}, "time": 60}, "22": {"q1": 1, "q3": 4, "q2": 70, "bb": {"h": 495, "startX": 175, "startY": 3, "w": 323}, "time": 24}, "23": {"q1": 1, "q3": 4, "q2": 70, "bb": {"h": -242, "startX": 498, "startY": 3, "w": 219}, "time": 38}, "24": {"q1": 1, "q3": 3, "q2": 70, "bb": {"h": 308, "startX": 22, "startY": 192, "w": 310}, "time": 21}, "demographic": {"major": "YES", "estimation": "No", "gender": "Female", "nativeLanguage": "ENGLISH", "job": "MANAGER", "nativeSpeaker": "Yes", "education": "Master's", "stayInUS": "Native (all my life)"}, "name": "A1P7SNEPLJ1X2A"}, {"1": {"q1": 0, "q3": 4, "q2": 80, "bb": {"h": 136, "startX": 12, "startY": 12, "w": 184}, "time": 24}, "2": {"q1": 0, "q3": 3, "q2": 60, "bb": {"h": 70, "startX": 12, "startY": 114, "w": 177}, "time": 20}, "3": {"q1": 1, "q3": 1, "q2": 100, "bb": {"h": 148, "startX": 36, "startY": 155, "w": 153}, "time": 17}, "4": {"q1": 1, "q3": 1, "q2": 100, "bb": {"h": 112, "startX": 66, "startY": 263, "w": 181}, "time": 37}, "5": {"q1": 0, "q3": 4, "q2": 80, "bb": {"h": 207, "startX": 190, "startY": 201, "w": 236}, "time": 23}, "6": {"q1": 0, "q3": 3, "q2": 90, "bb": {"h": 157, "startX": 88, "startY": 129, "w": 180}, "time": 20}, "7": {"q1": 0, "q3": 3, "q2": 40, "bb": {"h": 129, "startX": 123, "startY": 336, "w": 183}, "time": 23}, "8": {"q1": 0, "q3": 4, "q2": 80, "bb": {"h": 101, "startX": 153, "startY": 392, "w": 139}, "time": 25}, "9": {"q1": 0, "q3": 3, "q2": 30, "bb": {"h": 136, "startX": 485, "startY": 490, "w": 194}, "time": 23}, "10": {"q1": 0, "q3": 3, "q2": 50, "bb": {"h": 151, "startX": 379, "startY": 213, "w": 99}, "time": 19}, "11": {"q1": 0, "q3": 3, "q2": 60, "bb": {"h": 136, "startX": 345, "startY": 6, "w": 150}, "time": 35}, "12": {"q1": 0, "q3": 3, "q2": 100, "bb": {"h": 150, "startX": 4, "startY": 203, "w": 134}, "time": 23}, "13": {"q1": 0, "q3": 4, "q2": 80, "bb": {"h": 142, "startX": 184, "startY": 65, "w": 140}, "time": 25}, "14": {"q1": 0, "q3": 3, "q2": 90, "bb": {"h": 80, "startX": 23, "startY": 414, "w": 157}, "time": 32}, "15": {"q1": 0, "q3": 2, "q2": 90, "bb": {"h": 142, "startX": 1, "startY": 84, "w": 49}, "time": 17}, "16": {"q1": 0, "q3": 4, "q2": 100, "bb": {"h": 180, "startX": 213, "startY": 494, "w": 183}, "time": 25}, "17": {"q1": 0, "q3": 4, "q2": 90, "bb": {"h": 100, "startX": 242, "startY": 363, "w": 126}, "time": 39}, "18": {"q1": 0, "q3": 4, "q2": 30, "bb": {"h": 154, "startX": 98, "startY": 116, "w": 117}, "time": 25}, "19": {"q1": 0, "q3": 4, "q2": 100, "bb": {"h": 146, "startX": 14, "startY": 97, "w": 88}, "time": 27}, "20": {"q1": 0, "q3": 4, "q2": 90, "bb": {"h": 94, "startX": 84, "startY": 9, "w": 207}, "time": 17}, "21": {"q1": 0, "q3": 3, "q2": 90, "bb": {"h": 137, "startX": 127, "startY": 72, "w": 154}, "time": 32}, "22": {"q1": 0, "q3": 3, "q2": 90, "bb": {"h": 81, "startX": 99, "startY": 237, "w": 117}, "time": 14}, "23": {"q1": 0, "q3": 4, "q2": 80, "bb": {"h": 94, "startX": 12, "startY": 344, "w": 120}, "time": 36}, "24": {"q1": 0, "q3": 4, "q2": 50, "bb": {"h": 114, "startX": 231, "startY": 103, "w": 121}, "time": 37}, "demographic": {"major": "COMPUTER SCIENCE", "estimation": "No", "gender": "Female", "age": "35", "job": "DATA ANALYST", "nativeSpeaker": "Yes", "employed": "Yes", "education": "4 year degree", "stayInUS": "Native (all my life)"}, "name": "A2R93OEJ9TOWV6"}, {"1": {"q1": 1, "q3": 3, "q2": 70, "bb": {"h": 351, "startX": 38, "startY": 13, "w": 455}, "time": 28}, "2": {"q1": 0, "q3": 2, "q2": 30, "bb": {"h": null, "startX": 26, "startY": 34, "w": null}, "time": 25}, "3": {"q1": 1, "q3": 1, "q2": 100, "bb": {"h": 225, "startX": 31, "startY": 113, "w": 165}, "time": 32}, "4": {"q1": 1, "q3": 1, "q2": 100, "bb": {"h": 139, "startX": 56, "startY": 277, "w": 158}, "time": 24}, "5": {"q1": 1, "q3": 4, "q2": 30, "bb": {"h": 351, "startX": 70, "startY": 82, "w": 344}, "time": 24}, "6": {"q1": 1, "q3": 3, "q2": 70, "bb": {"h": 343, "startX": 34, "startY": 28, "w": 412}, "time": 23}, "7": {"q1": 1, "q3": 2, "q2": 70, "bb": {"h": 345, "startX": 489, "startY": 443, "w": 422}, "time": 19}, "8": {"q1": 0, "q3": 2, "q2": 20, "bb": {"h": 328, "startX": 33, "startY": 103, "w": 436}, "time": 19}, "9": {"q1": 1, "q3": 2, "q2": 80, "bb": {"h": 329, "startX": 24, "startY": 22, "w": 438}, "time": 20}, "10": {"q1": 0, "q3": 3, "q2": 30, "bb": {"h": 253, "startX": 11, "startY": 23, "w": 358}, "time": 34}, "11": {"q1": 1, "q3": 2, "q2": 60, "bb": {"h": 344, "startX": 59, "startY": 44, "w": 346}, "time": 34}, "12": {"q1": 1, "q3": 4, "q2": 30, "bb": {"h": 345, "startX": 39, "startY": 43, "w": 450}, "time": 25}, "13": {"q1": 1, "q3": 2, "q2": 60, "bb": {"h": 291, "startX": 40, "startY": 162, "w": 418}, "time": 52}, "14": {"q1": 1, "q3": 2, "q2": 90, "bb": {"h": 207, "startX": 5, "startY": 7, "w": 332}, "time": 33}, "15": {"q1": 1, "q3": 4, "q2": 40, "bb": {"h": 313, "startX": 24, "startY": 102, "w": 464}, "time": 22}, "16": {"q1": 0, "q3": 2, "q2": 20, "bb": {"h": 340, "startX": 80, "startY": 46, "w": 399}, "time": 32}, "17": {"q1": 0, "q3": 2, "q2": 20, "bb": {"h": 155, "startX": 144, "startY": 346, "w": 353}, "time": 21}, "18": {"q1": 1, "q3": 2, "q2": 80, "bb": {"h": 298, "startX": 51, "startY": 148, "w": 446}, "time": 26}, "19": {"q1": 1, "q3": 2, "q2": 80, "bb": {"h": 247, "startX": 36, "startY": 169, "w": 461}, "time": 26}, "20": {"q1": 1, "q3": 2, "q2": 70, "bb": {"h": 386, "startX": 51, "startY": 23, "w": 449}, "time": 17}, "21": {"q1": 0, "q3": 3, "q2": 20, "bb": {"h": 319, "startX": 78, "startY": 95, "w": 373}, "time": 29}, "22": {"q1": 1, "q3": 2, "q2": 90, "bb": {"h": 295, "startX": 25, "startY": 166, "w": 417}, "time": 17}, "23": {"q1": 1, "q3": 2, "q2": 70, "bb": {"h": 156, "startX": 65, "startY": 340, "w": 373}, "time": 19}, "24": {"q1": 1, "q3": 2, "q2": 70, "bb": {"h": 328, "startX": 27, "startY": 34, "w": 416}, "time": 27}, "demographic": {"major": "B.Phil.", "estimation": "No", "specify": "NOTHING", "gender": "Male", "age": "33", "nativeLanguage": "NOTHING", "job": "MANUFACTURING", "nativeSpeaker": "Yes", "employed": "Yes", "education": "Some College", "stayInUS": "Greater than 5 years"}, "name": "A3FJJVBZPF9NSD"}, {"1": {"q1": 0, "q3": 3, "q2": 80, "bb": {"h": 48, "startX": 244, "startY": 160, "w": 10}, "time": 46}, "2": {"q1": 0, "q3": 2, "q2": 80, "bb": {"h": 21, "startX": 8, "startY": 281, "w": 32}, "time": 33}, "3": {"q1": 1, "q3": 2, "q2": 100, "bb": {"h": 137, "startX": 32, "startY": 163, "w": 120}, "time": 16}, "4": {"q1": 1, "q3": 1, "q2": 100, "bb": {"h": 96, "startX": 72, "startY": 283, "w": 142}, "time": 17}, "5": {"q1": 0, "q3": 3, "q2": 80, "bb": {"h": 13, "startX": 350, "startY": 380, "w": 22}, "time": 44}, "6": {"q1": 0, "q3": 3, "q2": 80, "bb": {"h": 30, "startX": 218, "startY": 247, "w": 28}, "time": 45}, "7": {"q1": 0, "q3": 3, "q2": 70, "bb": {"h": 31, "startX": 267, "startY": 434, "w": 25}, "time": 46}, "8": {"q1": 0, "q3": 3, "q2": 90, "bb": {"h": 38, "startX": 17, "startY": 275, "w": 21}, "time": 25}, "9": {"q1": 0, "q3": 3, "q2": 70, "bb": {"h": 23, "startX": 303, "startY": 356, "w": 23}, "time": 47}, "10": {"q1": 0, "q3": 3, "q2": 80, "bb": {"h": 44, "startX": 5, "startY": 249, "w": 18}, "time": 42}, "11": {"q1": 0, "q3": 3, "q2": 70, "bb": {"h": 17, "startX": 117, "startY": 185, "w": 27}, "time": 60}, "12": {"q1": 0, "q3": 3, "q2": 60, "bb": {"h": 44, "startX": 5, "startY": 48, "w": 14}, "time": 51}, "13": {"q1": 0, "q3": 2, "q2": 80, "bb": {"h": 79, "startX": 451, "startY": 168, "w": 41}, "time": 36}, "14": {"q1": 0, "q3": 2, "q2": 70, "bb": {"h": 16, "startX": 162, "startY": 227, "w": 26}, "time": 51}, "15": {"q1": 0, "q3": 2, "q2": 80, "bb": {"h": 30, "startX": 196, "startY": 1, "w": 38}, "time": 29}, "16": {"q1": 0, "q3": 3, "q2": 80, "bb": {"h": 47, "startX": 413, "startY": 278, "w": 9}, "time": 35}, "17": {"q1": 0, "q3": 2, "q2": 90, "bb": {"h": 27, "startX": 247, "startY": 84, "w": 33}, "time": 27}, "18": {"q1": 0, "q3": 2, "q2": 80, "bb": {"h": 26, "startX": 299, "startY": 416, "w": 38}, "time": 36}, "19": {"q1": 0, "q3": 2, "q2": 90, "bb": {"h": 47, "startX": 307, "startY": 290, "w": 27}, "time": 32}, "20": {"q1": 0, "q3": 2, "q2": 80, "bb": {"h": 61, "startX": 459, "startY": 308, "w": 34}, "time": 30}, "21": {"q1": 0, "q3": 2, "q2": 90, "bb": {"h": -13, "startX": 148, "startY": 430, "w": 71}, "time": 34}, "22": {"q1": 0, "q3": 2, "q2": 80, "bb": {"h": -28, "startX": 251, "startY": 281, "w": 14}, "time": 35}, "23": {"q1": 0, "q3": 2, "q2": 80, "bb": {"h": 21, "startX": 224, "startY": 11, "w": 30}, "time": 34}, "24": {"q1": 0, "q3": 2, "q2": 80, "bb": {"h": 16, "startX": 456, "startY": 51, "w": 15}, "time": 38}, "demographic": {"major": "computer science", "estimation": "No", "gender": "Female", "age": "31", "nativeLanguage": "English", "job": "finance", "nativeSpeaker": "Yes", "employed": "Yes", "education": "4 year degree", "stayInUS": "Native (all my life)"}, "name": "A2UO993IW1XVO1"}, {"1": {"q1": 0, "q3": 4, "q2": 70, "bb": {"h": 184, "startX": 353, "startY": 23, "w": 103}, "time": 11}, "2": {"q1": 0, "q3": 4, "q2": 70, "bb": {"h": 189, "startX": 85, "startY": 59, "w": 130}, "time": 29}, "3": {"q1": 1, "q3": 1, "q2": 100, "bb": {"h": 152, "startX": 48, "startY": 151, "w": 103}, "time": 18}, "4": {"q1": 1, "q3": 1, "q2": 100, "bb": {"h": 126, "startX": 64, "startY": 270, "w": 158}, "time": 11}, "5": {"q1": 0, "q3": 4, "q2": 80, "bb": {"h": 124, "startX": 71, "startY": 28, "w": 147}, "time": 18}, "6": {"q1": 1, "q3": 3, "q2": 80, "bb": {"h": 197, "startX": 497, "startY": 262, "w": 125}, "time": 26}, "7": {"q1": 0, "q3": 3, "q2": 80, "bb": {"h": 163, "startX": 385, "startY": 274, "w": 108}, "time": 14}, "8": {"q1": 1, "q3": 3, "q2": 90, "bb": {"h": 142, "startX": 369, "startY": 311, "w": 123}, "time": 42}, "9": {"q1": 0, "q3": 4, "q2": 80, "bb": {"h": 89, "startX": 178, "startY": 11, "w": 143}, "time": 28}, "10": {"q1": 0, "q3": 3, "q2": 70, "bb": {"h": 134, "startX": 51, "startY": 257, "w": 168}, "time": 17}, "11": {"q1": 0, "q3": 4, "q2": 70, "bb": {"h": 230, "startX": 217, "startY": 125, "w": 155}, "time": 20}, "12": {"q1": 0, "q3": 3, "q2": 70, "bb": {"h": 132, "startX": 214, "startY": 29, "w": 175}, "time": 47}, "13": {"q1": 1, "q3": 3, "q2": 70, "bb": {"h": 168, "startX": 123, "startY": 68, "w": 214}, "time": 13}, "14": {"q1": 1, "q3": 3, "q2": 90, "bb": {"h": 92, "startX": 42, "startY": 1, "w": 143}, "time": 17}, "15": {"q1": 0, "q3": 4, "q2": 80, "bb": {"h": 459, "startX": 457, "startY": 467, "w": 429}, "time": 45}, "16": {"q1": 0, "q3": 4, "q2": 90, "bb": {"h": 78, "startX": 262, "startY": 3, "w": 94}, "time": 33}, "17": {"q1": 1, "q3": 3, "q2": 90, "bb": {"h": 122, "startX": 244, "startY": 364, "w": 170}, "time": 33}, "18": {"q1": 0, "q3": 3, "q2": 70, "bb": {"h": 162, "startX": 122, "startY": 137, "w": 83}, "time": 16}, "19": {"q1": 0, "q3": 4, "q2": 70, "bb": {"h": 193, "startX": 303, "startY": 40, "w": 146}, "time": 27}, "20": {"q1": 0, "q3": 4, "q2": 80, "bb": {"h": 161, "startX": 124, "startY": 241, "w": 111}, "time": 17}, "21": {"q1": 0, "q3": 3, "q2": 90, "bb": {"h": 134, "startX": 199, "startY": 36, "w": 193}, "time": 20}, "22": {"q1": 0, "q3": 4, "q2": 70, "bb": {"h": 165, "startX": 87, "startY": 209, "w": 178}, "time": 10}, "23": {"q1": 0, "q3": 3, "q2": 60, "bb": {"h": 175, "startX": 95, "startY": 126, "w": 122}, "time": 23}, "24": {"q1": 1, "q3": 1, "q2": 70, "bb": {"h": 170, "startX": 75, "startY": 6, "w": 107}, "time": 27}, "demographic": {"major": "Computer science", "estimation": "No", "gender": "Female", "age": "27", "job": "Manager", "nativeSpeaker": "Yes", "employed": "Yes", "education": "Master's", "stayInUS": "Greater than 5 years"}, "name": "A2TFJFPIVF2UBT"}, {"1": {"q1": 0, "q3": 3, "q2": 70, "bb": {"h": 92, "startX": 131, "startY": 339, "w": 140}, "time": 32}, "2": {"q1": 0, "q3": 3, "q2": 80, "bb": {"h": 101, "startX": 314, "startY": 379, "w": 163}, "time": 25}, "3": {"q1": 0, "q3": 2, "q2": 70, "bb": {"h": 91, "startX": 213, "startY": 24, "w": 109}, "time": 24}, "4": {"q1": 1, "q3": 1, "q2": 100, "bb": {"h": 93, "startX": 71, "startY": 280, "w": 139}, "time": 19}, "5": {"q1": 0, "q3": 2, "q2": 100, "bb": {"h": 102, "startX": 54, "startY": 252, "w": 106}, "time": 33}, "6": {"q1": 0, "q3": 2, "q2": 80, "bb": {"h": 129, "startX": 310, "startY": 217, "w": 116}, "time": 25}, "7": {"q1": 0, "q3": 2, "q2": 80, "bb": {"h": 102, "startX": 103, "startY": 43, "w": 129}, "time": 28}, "8": {"q1": 0, "q3": 2, "q2": 80, "bb": {"h": 119, "startX": 141, "startY": 344, "w": 194}, "time": 36}, "9": {"q1": 0, "q3": 3, "q2": 80, "bb": {"h": 123, "startX": 30, "startY": 256, "w": 129}, "time": 43}, "10": {"q1": 0, "q3": 2, "q2": 80, "bb": {"h": 96, "startX": 311, "startY": 256, "w": 129}, "time": 26}, "11": {"q1": 0, "q3": 2, "q2": 90, "bb": {"h": 123, "startX": 271, "startY": 216, "w": 130}, "time": 21}, "12": {"q1": 0, "q3": 2, "q2": 80, "bb": {"h": 119, "startX": 280, "startY": 226, "w": 146}, "time": 36}, "13": {"q1": 0, "q3": 3, "q2": 80, "bb": {"h": 87, "startX": 120, "startY": 369, "w": 118}, "time": 26}, "14": {"q1": 0, "q3": 3, "q2": 90, "bb": {"h": 148, "startX": 327, "startY": 338, "w": 122}, "time": 28}, "15": {"q1": 0, "q3": 3, "q2": 80, "bb": {"h": 119, "startX": 321, "startY": 360, "w": 150}, "time": 32}, "16": {"q1": 0, "q3": 2, "q2": 70, "bb": {"h": 109, "startX": 173, "startY": 252, "w": 115}, "time": 35}, "17": {"q1": 0, "q3": 2, "q2": 80, "bb": {"h": 115, "startX": 14, "startY": 133, "w": 91}, "time": 32}, "18": {"q1": 0, "q3": 3, "q2": 70, "bb": {"h": 106, "startX": 284, "startY": 62, "w": 125}, "time": 23}, "19": {"q1": 0, "q3": 3, "q2": 80, "bb": {"h": 133, "startX": 27, "startY": 366, "w": 129}, "time": 33}, "20": {"q1": 0, "q3": 3, "q2": 70, "bb": {"h": 101, "startX": 316, "startY": 36, "w": 101}, "time": 30}, "21": {"q1": 0, "q3": 3, "q2": 90, "bb": {"h": 129, "startX": 63, "startY": 177, "w": 116}, "time": 33}, "22": {"q1": 0, "q3": 2, "q2": 90, "bb": {"h": 123, "startX": 340, "startY": 128, "w": 130}, "time": 33}, "23": {"q1": 0, "q3": 2, "q2": 80, "bb": {"h": 118, "startX": 102, "startY": 195, "w": 122}, "time": 27}, "24": {"q1": 0, "q3": 2, "q2": 80, "bb": {"h": 128, "startX": 41, "startY": 74, "w": 121}, "time": 41}, "demographic": {"major": "Computer science", "estimation": "No", "gender": "Female", "age": "25", "job": "Mid level manager", "nativeSpeaker": "Yes", "employed": "Yes", "education": "Master's", "stayInUS": "Greater than 5 years"}, "name": "A2PC7ZR3H58N7I"}, {"1": {"q1": 0, "q3": 2, "q2": 90, "bb": {"h": 155, "startX": 53, "startY": 173, "w": 172}, "time": 28}, "2": {"q1": 0, "q3": 2, "q2": 90, "bb": {"h": 138, "startX": 134, "startY": 68, "w": 218}, "time": 12}, "3": {"q1": 0, "q3": 2, "q2": 90, "bb": {"h": 127, "startX": 289, "startY": 138, "w": 167}, "time": 13}, "4": {"q1": 1, "q3": 2, "q2": 100, "bb": {"h": 109, "startX": 63, "startY": 278, "w": 185}, "time": 10}, "5": {"q1": 0, "q3": 4, "q2": 90, "bb": {"h": 166, "startX": 42, "startY": 85, "w": 163}, "time": 14}, "6": {"q1": 0, "q3": 2, "q2": 90, "bb": {"h": 123, "startX": 307, "startY": 44, "w": 168}, "time": 37}, "7": {"q1": 0, "q3": 2, "q2": 90, "bb": {"h": 167, "startX": 249, "startY": 32, "w": 208}, "time": 19}, "8": {"q1": 0, "q3": 3, "q2": 80, "bb": {"h": 130, "startX": 19, "startY": 55, "w": 164}, "time": 15}, "9": {"q1": 0, "q3": 4, "q2": 90, "bb": {"h": 143, "startX": 70, "startY": 343, "w": 173}, "time": 31}, "10": {"q1": 0, "q3": 2, "q2": 90, "bb": {"h": 118, "startX": 267, "startY": 88, "w": 176}, "time": 16}, "11": {"q1": 0, "q3": 2, "q2": 80, "bb": {"h": 140, "startX": 279, "startY": 63, "w": 174}, "time": 22}, "12": {"q1": 0, "q3": 2, "q2": 90, "bb": {"h": 145, "startX": 294, "startY": 224, "w": 163}, "time": 28}, "13": {"q1": 0, "q3": 2, "q2": 90, "bb": {"h": 161, "startX": 32, "startY": 74, "w": 168}, "time": 14}, "14": {"q1": 0, "q3": 3, "q2": 80, "bb": {"h": 170, "startX": 278, "startY": 47, "w": 181}, "time": 22}, "15": {"q1": 0, "q3": 4, "q2": 90, "bb": {"h": 188, "startX": 78, "startY": 87, "w": 168}, "time": 16}, "16": {"q1": 0, "q3": 2, "q2": 80, "bb": {"h": 139, "startX": 105, "startY": 264, "w": 166}, "time": 60}, "17": {"q1": 0, "q3": 3, "q2": 90, "bb": {"h": 165, "startX": 368, "startY": 112, "w": 129}, "time": 24}, "18": {"q1": 0, "q3": 3, "q2": 90, "bb": {"h": 147, "startX": 32, "startY": 131, "w": 188}, "time": 30}, "19": {"q1": 0, "q3": 2, "q2": 80, "bb": {"h": 133, "startX": 19, "startY": 324, "w": 155}, "time": 18}, "20": {"q1": 0, "q3": 2, "q2": 90, "bb": {"h": 170, "startX": 32, "startY": 55, "w": 213}, "time": 30}, "21": {"q1": 0, "q3": 2, "q2": 90, "bb": {"h": 118, "startX": 46, "startY": 104, "w": 155}, "time": 17}, "22": {"q1": 0, "q3": 2, "q2": 80, "bb": {"h": 131, "startX": 185, "startY": 28, "w": 149}, "time": 27}, "23": {"q1": 0, "q3": 2, "q2": 90, "bb": {"h": 116, "startX": 55, "startY": 40, "w": 147}, "time": 46}, "24": {"q1": 0, "q3": 2, "q2": 90, "bb": {"h": 134, "startX": 39, "startY": 139, "w": 179}, "time": 17}, "demographic": {"estimation": "No", "gender": "Female", "age": "25", "job": "Manager ", "nativeSpeaker": "Yes", "employed": "Yes", "education": "Master's", "stayInUS": "Native (all my life)"}, "name": "A3745K0LN6ASHZ"}, {"1": {"q1": 1, "q3": 1, "q2": 100, "bb": {"h": null, "startX": 251, "startY": 258, "w": null}, "time": 23}, "2": {"q1": 0, "q3": 1, "q2": 100, "bb": {"h": null, "startX": 266, "startY": 327, "w": null}, "time": 15}, "3": {"q1": 1, "q3": 1, "q2": 90, "bb": {"h": null, "startX": 270, "startY": 296, "w": null}, "time": 13}, "4": {"q1": 1, "q3": 1, "q2": 100, "bb": {"h": null, "startX": 286, "startY": 267, "w": null}, "time": 14}, "5": {"q1": 1, "q3": 1, "q2": 100, "bb": {"h": null, "startX": 270, "startY": 314, "w": null}, "time": 28}, "6": {"q1": 1, "q3": 1, "q2": 100, "bb": {"h": 20, "startX": 468, "startY": 106, "w": -51}, "time": 61}, "7": {"q1": 1, "q3": 1, "q2": 100, "bb": {"h": 1, "startX": 245, "startY": 245, "w": 0}, "time": 13}, "8": {"q1": 1, "q3": 2, "q2": 90, "bb": {"h": null, "startX": 428, "startY": 352, "w": null}, "time": 61}, "9": {"q1": 0, "q3": 2, "q2": 100, "bb": {"h": null, "startX": 224, "startY": 121, "w": null}, "time": 17}, "10": {"q1": 0, "q3": 1, "q2": 100, "bb": {"h": null, "startX": 275, "startY": 245, "w": null}, "time": 14}, "11": {"q1": 1, "q3": 1, "q2": 100, "bb": {"h": null, "startX": 305, "startY": 296, "w": null}, "time": 17}, "12": {"q1": 1, "q3": 1, "q2": 100, "bb": {"h": null, "startX": 365, "startY": 229, "w": null}, "time": 62}, "13": {"q1": 1, "q3": 1, "q2": 90, "bb": {"h": null, "startX": 305, "startY": 227, "w": null}, "time": 19}, "14": {"q1": 1, "q3": 1, "q2": 90, "bb": {"h": 1, "startX": 242, "startY": 272, "w": 0}, "time": 14}, "15": {"q1": 1, "q3": 1, "q2": 90, "bb": {"h": null, "startX": 360, "startY": 252, "w": null}, "time": 18}, "16": {"q1": 1, "q3": 1, "q2": 100, "bb": {"h": 1, "startX": 257, "startY": 244, "w": -1}, "time": 17}, "17": {"q1": 0, "q3": 1, "q2": 90, "bb": {"h": null, "startX": 253, "startY": 301, "w": null}, "time": 13}, "18": {"q1": 1, "q3": 1, "q2": 100, "bb": {"h": null, "startX": 253, "startY": 286, "w": null}, "time": 17}, "19": {"q1": 1, "q3": 1, "q2": 90, "bb": {"h": null, "startX": 192, "startY": 276, "w": null}, "time": 17}, "20": {"q1": 0, "q3": 1, "q2": 90, "bb": {"h": null, "startX": 283, "startY": 345, "w": null}, "time": 15}, "21": {"q1": 1, "q3": 3, "q2": 80, "bb": {"h": null, "startX": 195, "startY": 310, "w": null}, "time": 62}, "22": {"q1": 0, "q3": 1, "q2": 100, "bb": {"h": null, "startX": 327, "startY": 285, "w": null}, "time": 44}, "23": {"q1": 0, "q3": 1, "q2": 100, "bb": {"h": null, "startX": 317, "startY": 246, "w": null}, "time": 14}, "24": {"q1": 0, "q3": 2, "q2": 100, "bb": {"h": 0, "startX": 191, "startY": 217, "w": 1}, "time": 24}, "demographic": {"major": "Postsecondary education includes universities and colleges, as well as trade and vocational schools.", "estimation": "Yes", "specify": "MainActivity to App and it started working", "gender": "Male", "age": "35", "nativeLanguage": "English", "job": "marketing manager", "nativeSpeaker": "Yes", "employed": "Yes", "education": "Master's", "stayInUS": "Greater than 5 years"}, "name": "A28XEO3QCICMAP"}, {"1": {"q1": 0, "q3": 4, "q2": 90, "bb": {"h": 58, "startX": 123, "startY": 368, "w": 109}, "time": 17}, "2": {"q1": 1, "q3": 3, "q2": 60, "bb": {"h": 73, "startX": 131, "startY": 52, "w": 105}, "time": 22}, "3": {"q1": 0, "q3": 3, "q2": 80, "bb": {"h": 17, "startX": 161, "startY": 466, "w": 103}, "time": 54}, "4": {"q1": 1, "q3": 3, "q2": 90, "bb": {"h": 56, "startX": 92, "startY": 289, "w": 118}, "time": 14}, "5": {"q1": 1, "q3": 3, "q2": 90, "bb": {"h": -12, "startX": 82, "startY": 35, "w": 99}, "time": 28}, "6": {"q1": 1, "q3": 4, "q2": 90, "bb": {"h": 50, "startX": 444, "startY": 65, "w": 50}, "time": 25}, "7": {"q1": 1, "q3": 3, "q2": 90, "bb": {"h": 65, "startX": 18, "startY": 26, "w": 26}, "time": 25}, "8": {"q1": 1, "q3": 3, "q2": 90, "bb": {"h": 95, "startX": 101, "startY": 322, "w": 71}, "time": 62}, "9": {"q1": 0, "q3": 2, "q2": 90, "bb": {"h": 34, "startX": 258, "startY": 271, "w": 132}, "time": 18}, "10": {"q1": 0, "q3": 4, "q2": 30, "bb": {"h": 25, "startX": 56, "startY": 198, "w": 103}, "time": 19}, "11": {"q1": 1, "q3": 3, "q2": 90, "bb": {"h": 90, "startX": 368, "startY": 140, "w": -35}, "time": 19}, "12": {"q1": 0, "q3": 4, "q2": 80, "bb": {"h": 55, "startX": 219, "startY": 203, "w": 139}, "time": 17}, "13": {"q1": 1, "q3": 2, "q2": 80, "bb": {"h": null, "startX": 170, "startY": 125, "w": null}, "time": 23}, "14": {"q1": 1, "q3": 2, "q2": 90, "bb": {"h": 93, "startX": 475, "startY": 198, "w": 16}, "time": 13}, "15": {"q1": 1, "q3": 3, "q2": 80, "bb": {"h": 65, "startX": 39, "startY": 31, "w": 82}, "time": 14}, "16": {"q1": 0, "q3": 3, "q2": 100, "bb": {"h": 50, "startX": 255, "startY": 239, "w": 157}, "time": 57}, "17": {"q1": 0, "q3": 3, "q2": 80, "bb": {"h": 8, "startX": 116, "startY": 435, "w": 117}, "time": 36}, "18": {"q1": 1, "q3": 3, "q2": 80, "bb": {"h": 128, "startX": 158, "startY": 147, "w": -36}, "time": 16}, "19": {"q1": 1, "q3": 2, "q2": 80, "bb": {"h": 47, "startX": 384, "startY": 295, "w": 56}, "time": 17}, "20": {"q1": 1, "q3": 4, "q2": 90, "bb": {"h": 69, "startX": 239, "startY": 96, "w": 115}, "time": 38}, "21": {"q1": 0, "q3": 2, "q2": 30, "bb": {"h": 82, "startX": 121, "startY": 414, "w": -48}, "time": 22}, "22": {"q1": 0, "q3": 2, "q2": 90, "bb": {"h": 61, "startX": 272, "startY": 428, "w": 77}, "time": 14}, "23": {"q1": 0, "q3": 4, "q2": 80, "bb": {"h": 65, "startX": 309, "startY": 263, "w": 80}, "time": 26}, "24": {"q1": 0, "q3": 3, "q2": 70, "bb": {"h": 109, "startX": 252, "startY": 311, "w": 56}, "time": 26}, "demographic": {"major": "Computer Science", "estimation": "No", "gender": "Female", "age": "57", "job": "Engineer", "nativeSpeaker": "Yes", "employed": "Yes", "education": "Master's", "stayInUS": "Greater than 5 years"}, "name": "A2UC3CDVQNVPQ8"}, {"1": {"q1": 0, "q3": 1, "q2": 50, "bb": {"h": null, "startX": 252, "startY": 204, "w": null}, "time": 41}, "2": {"q1": 0, "q3": 3, "q2": 50, "bb": {"h": null, "startX": 255, "startY": 246, "w": null}, "time": 31}, "3": {"q1": 1, "q3": 2, "q2": 100, "bb": {"h": null, "startX": 191, "startY": 346, "w": null}, "time": 30}, "4": {"q1": 1, "q3": 1, "q2": 100, "bb": {"h": 83, "startX": 67, "startY": 286, "w": 150}, "time": 28}, "5": {"q1": 0, "q3": 3, "q2": 50, "bb": {"h": null, "startX": 212, "startY": 321, "w": null}, "time": 40}, "6": {"q1": 0, "q3": 2, "q2": 50, "bb": {"h": 0, "startX": 257, "startY": 267, "w": -1}, "time": 33}, "7": {"q1": 0, "q3": 3, "q2": 50, "bb": {"h": null, "startX": 292, "startY": 200, "w": null}, "time": 39}, "8": {"q1": 0, "q3": 3, "q2": 50, "bb": {"h": 0, "startX": 168, "startY": 361, "w": 0}, "time": 43}, "9": {"q1": 0, "q3": 3, "q2": 50, "bb": {"h": null, "startX": 240, "startY": 298, "w": null}, "time": 38}, "10": {"q1": 0, "q3": 3, "q2": 50, "bb": {"h": null, "startX": 244, "startY": 211, "w": null}, "time": 44}, "11": {"q1": 0, "q3": 3, "q2": 50, "bb": {"h": 0, "startX": 225, "startY": 210, "w": -1}, "time": 28}, "12": {"q1": 0, "q3": 3, "q2": 50, "bb": {"h": null, "startX": 317, "startY": 221, "w": null}, "time": 44}, "13": {"q1": 0, "q3": 3, "q2": 30, "bb": {"h": null, "startX": 272, "startY": 234, "w": null}, "time": 49}, "14": {"q1": 0, "q3": 2, "q2": 50, "bb": {"h": null, "startX": 236, "startY": 260, "w": null}, "time": 41}, "15": {"q1": 0, "q3": 3, "q2": 70, "bb": {"h": null, "startX": 280, "startY": 398, "w": null}, "time": 30}, "16": {"q1": 0, "q3": 3, "q2": 40, "bb": {"h": 391, "startX": 35, "startY": 100, "w": 331}, "time": 49}, "17": {"q1": 0, "q3": 3, "q2": 50, "bb": {"h": null, "startX": 228, "startY": 285, "w": null}, "time": 22}, "18": {"q1": 0, "q3": 3, "q2": 50, "bb": {"h": null, "startX": 264, "startY": 329, "w": null}, "time": 35}, "19": {"q1": 0, "q3": 2, "q2": 50, "bb": {"h": null, "startX": 237, "startY": 251, "w": null}, "time": 40}, "20": {"q1": 0, "q3": 3, "q2": 40, "bb": {"h": null, "startX": 289, "startY": 236, "w": null}, "time": 48}, "21": {"q1": 0, "q3": 3, "q2": 50, "bb": {"h": null, "startX": 264, "startY": 234, "w": null}, "time": 47}, "22": {"q1": 0, "q3": 3, "q2": 40, "bb": {"h": null, "startX": 263, "startY": 280, "w": null}, "time": 46}, "23": {"q1": 0, "q3": 3, "q2": 40, "bb": {"h": null, "startX": 273, "startY": 259, "w": null}, "time": 53}, "24": {"q1": 0, "q3": 3, "q2": 50, "bb": {"h": null, "startX": 274, "startY": 348, "w": null}, "time": 30}, "demographic": {"major": "Computer science", "estimation": "No", "gender": "Male", "age": "30", "job": "Supervisor", "nativeSpeaker": "Yes", "employed": "Yes", "education": "Master's", "stayInUS": "Native (all my life)"}, "name": "AS4FVWL91C6HR"}, {"1": {"q1": 1, "q3": 2, "q2": 60, "bb": {"h": -409, "startX": 31, "startY": 479, "w": 381}, "time": 11}, "2": {"q1": 1, "q3": 3, "q2": 40, "bb": {"h": -185, "startX": 23, "startY": 199, "w": 476}, "time": 22}, "3": {"q1": 1, "q3": 2, "q2": 90, "bb": {"h": -181, "startX": 47, "startY": 333, "w": 178}, "time": 22}, "4": {"q1": 1, "q3": 2, "q2": 60, "bb": {"h": -139, "startX": 50, "startY": 412, "w": 234}, "time": 11}, "5": {"q1": 1, "q3": 2, "q2": 40, "bb": {"h": -189, "startX": 258, "startY": 439, "w": 243}, "time": 30}, "6": {"q1": 1, "q3": 3, "q2": 40, "bb": {"h": -356, "startX": 103, "startY": 405, "w": 376}, "time": 57}, "7": {"q1": 1, "q3": 2, "q2": 60, "bb": {"h": -417, "startX": 82, "startY": 460, "w": 408}, "time": 12}, "8": {"q1": 1, "q3": 2, "q2": 60, "bb": {"h": -329, "startX": 24, "startY": 332, "w": 361}, "time": 27}, "9": {"q1": 1, "q3": 2, "q2": 60, "bb": {"h": -389, "startX": 15, "startY": 497, "w": 436}, "time": 17}, "10": {"q1": 1, "q3": 2, "q2": 70, "bb": {"h": -203, "startX": 169, "startY": 489, "w": 314}, "time": 15}, "11": {"q1": 1, "q3": 3, "q2": 70, "bb": {"h": -290, "startX": 84, "startY": 450, "w": 360}, "time": 20}, "12": {"q1": 1, "q3": 2, "q2": 60, "bb": {"h": -275, "startX": 117, "startY": 388, "w": 283}, "time": 11}, "13": {"q1": 1, "q3": 3, "q2": 60, "bb": {"h": -328, "startX": 102, "startY": 396, "w": 359}, "time": 10}, "14": {"q1": 1, "q3": 3, "q2": 60, "bb": {"h": -124, "startX": 11, "startY": 483, "w": 163}, "time": 25}, "15": {"q1": 1, "q3": 2, "q2": 60, "bb": {"h": -394, "startX": 26, "startY": 476, "w": 307}, "time": 15}, "16": {"q1": 1, "q3": 2, "q2": 80, "bb": {"h": -170, "startX": 244, "startY": 482, "w": 228}, "time": 14}, "17": {"q1": 1, "q3": 2, "q2": 40, "bb": {"h": -140, "startX": 327, "startY": 493, "w": 171}, "time": 61}, "18": {"q1": 1, "q3": 2, "q2": 50, "bb": {"h": -200, "startX": 73, "startY": 421, "w": 336}, "time": 60}, "19": {"q1": 1, "q3": 2, "q2": 50, "bb": {"h": -246, "startX": 192, "startY": 272, "w": 267}, "time": 17}, "20": {"q1": 1, "q3": 2, "q2": 70, "bb": {"h": -188, "startX": 56, "startY": 279, "w": 194}, "time": 10}, "21": {"q1": 1, "q3": 2, "q2": 60, "bb": {"h": -207, "startX": 171, "startY": 431, "w": 316}, "time": 15}, "22": {"q1": 1, "q3": 2, "q2": 50, "bb": {"h": -189, "startX": 176, "startY": 307, "w": 270}, "time": 16}, "23": {"q1": 1, "q3": 2, "q2": 50, "bb": {"h": -236, "startX": 179, "startY": 251, "w": 314}, "time": 26}, "24": {"q1": 1, "q3": 2, "q2": 60, "bb": {"h": -307, "startX": 97, "startY": 432, "w": 399}, "time": 16}, "demographic": {"major": "Master degree", "estimation": "No", "gender": "Male", "age": "32", "nativeLanguage": "English", "job": "manager", "nativeSpeaker": "Yes", "employed": "Yes", "education": "Master's", "stayInUS": "Native (all my life)"}, "name": "A14EXILEA1MZTV"}, {"1": {"q1": 1, "q3": 2, "q2": 90, "bb": {"h": -2, "startX": 173, "startY": 359, "w": -1}, "time": 22}, "2": {"q1": 0, "q3": 4, "q2": 90, "bb": {"h": 0, "startX": 141, "startY": 241, "w": 0}, "time": 12}, "3": {"q1": 1, "q3": 2, "q2": 90, "bb": {"h": null, "startX": 263, "startY": 227, "w": null}, "time": 24}, "4": {"q1": 0, "q3": 4, "q2": 90, "bb": {"h": null, "startX": 233, "startY": 342, "w": null}, "time": 9}, "5": {"q1": 1, "q3": 2, "q2": 80, "bb": {"h": null, "startX": 133, "startY": 312, "w": null}, "time": 13}, "6": {"q1": 1, "q3": 3, "q2": 80, "bb": {"h": 0, "startX": 326, "startY": 140, "w": -2}, "time": 39}, "7": {"q1": 0, "q3": 3, "q2": 80, "bb": {"h": null, "startX": 400, "startY": 356, "w": null}, "time": 17}, "8": {"q1": 1, "q3": 3, "q2": 90, "bb": {"h": null, "startX": 226, "startY": 399, "w": null}, "time": 47}, "9": {"q1": 1, "q3": 2, "q2": 80, "bb": {"h": -1, "startX": 230, "startY": 326, "w": 2}, "time": 28}, "10": {"q1": 1, "q3": 3, "q2": 90, "bb": {"h": -1, "startX": 297, "startY": 420, "w": 0}, "time": 14}, "11": {"q1": 1, "q3": 3, "q2": 90, "bb": {"h": null, "startX": 302, "startY": 356, "w": null}, "time": 45}, "12": {"q1": 1, "q3": 2, "q2": 70, "bb": {"h": null, "startX": 265, "startY": 128, "w": null}, "time": 40}, "13": {"q1": 0, "q3": 2, "q2": 90, "bb": {"h": null, "startX": 261, "startY": 92, "w": null}, "time": 48}, "14": {"q1": 0, "q3": 3, "q2": 80, "bb": {"h": 0, "startX": 319, "startY": 162, "w": 0}, "time": 27}, "15": {"q1": 1, "q3": 3, "q2": 90, "bb": {"h": null, "startX": 381, "startY": 222, "w": null}, "time": 60}, "16": {"q1": 0, "q3": 3, "q2": 80, "bb": {"h": null, "startX": 189, "startY": 167, "w": null}, "time": 13}, "17": {"q1": 0, "q3": 3, "q2": 90, "bb": {"h": null, "startX": 278, "startY": 458, "w": null}, "time": 13}, "18": {"q1": 1, "q3": 2, "q2": 90, "bb": {"h": null, "startX": 255, "startY": 189, "w": null}, "time": 12}, "19": {"q1": 1, "q3": 2, "q2": 80, "bb": {"h": null, "startX": 294, "startY": 144, "w": null}, "time": 36}, "20": {"q1": 1, "q3": 2, "q2": 90, "bb": {"h": null, "startX": 286, "startY": 418, "w": null}, "time": 16}, "21": {"q1": 1, "q3": 2, "q2": 80, "bb": {"h": null, "startX": 236, "startY": 172, "w": null}, "time": 31}, "22": {"q1": 0, "q3": 3, "q2": 80, "bb": {"h": null, "startX": 219, "startY": 465, "w": null}, "time": 17}, "23": {"q1": 0, "q3": 2, "q2": 80, "bb": {"h": 0, "startX": 266, "startY": 126, "w": 0}, "time": 25}, "24": {"q1": 1, "q3": 2, "q2": 80, "bb": {"h": null, "startX": 268, "startY": 141, "w": null}, "time": 51}, "demographic": {"major": "computer", "estimation": "No", "gender": "Male", "age": "30", "job": "marketing", "nativeSpeaker": "Yes", "employed": "Yes", "education": "4 year degree", "stayInUS": "Native (all my life)"}, "name": "A2HYKOFCK1Q92D"}, {"1": {"q1": 0, "q3": 3, "q2": 80, "bb": {"h": 40, "startX": 238, "startY": 164, "w": 23}, "time": 31}, "2": {"q1": 0, "q3": 2, "q2": 90, "bb": {"h": 21, "startX": 19, "startY": 279, "w": 25}, "time": 28}, "3": {"q1": 1, "q3": 2, "q2": 100, "bb": {"h": 144, "startX": 38, "startY": 150, "w": 117}, "time": 17}, "4": {"q1": 1, "q3": 1, "q2": 100, "bb": {"h": 108, "startX": 77, "startY": 275, "w": 141}, "time": 13}, "5": {"q1": 0, "q3": 3, "q2": 70, "bb": {"h": 18, "startX": 209, "startY": 337, "w": 13}, "time": 60}, "6": {"q1": 0, "q3": 2, "q2": 80, "bb": {"h": 25, "startX": 233, "startY": 244, "w": 19}, "time": 38}, "7": {"q1": 0, "q3": 2, "q2": 80, "bb": {"h": 36, "startX": 269, "startY": 438, "w": 26}, "time": 41}, "8": {"q1": 0, "q3": 2, "q2": 80, "bb": {"h": 36, "startX": 17, "startY": 278, "w": 29}, "time": 41}, "9": {"q1": 0, "q3": 3, "q2": 80, "bb": {"h": 17, "startX": 302, "startY": 363, "w": 30}, "time": 41}, "10": {"q1": 0, "q3": 3, "q2": 90, "bb": {"h": 77, "startX": 1, "startY": 238, "w": 16}, "time": 21}, "11": {"q1": 0, "q3": 3, "q2": 80, "bb": {"h": 17, "startX": 15, "startY": 276, "w": 6}, "time": 33}, "12": {"q1": 0, "q3": 2, "q2": 80, "bb": {"h": 37, "startX": 3, "startY": 50, "w": 15}, "time": 21}, "13": {"q1": 0, "q3": 2, "q2": 100, "bb": {"h": 38, "startX": 475, "startY": 186, "w": 25}, "time": 25}, "14": {"q1": 0, "q3": 2, "q2": 90, "bb": {"h": 20, "startX": 165, "startY": 222, "w": 25}, "time": 21}, "15": {"q1": 0, "q3": 2, "q2": 90, "bb": {"h": 30, "startX": 198, "startY": 3, "w": 34}, "time": 18}, "16": {"q1": 0, "q3": 2, "q2": 90, "bb": {"h": -14, "startX": 69, "startY": 73, "w": 44}, "time": 31}, "17": {"q1": 0, "q3": 2, "q2": 80, "bb": {"h": 22, "startX": 242, "startY": 91, "w": 41}, "time": 40}, "18": {"q1": 0, "q3": 2, "q2": 90, "bb": {"h": 37, "startX": 294, "startY": 409, "w": 32}, "time": 37}, "19": {"q1": 0, "q3": 2, "q2": 90, "bb": {"h": 36, "startX": 300, "startY": 296, "w": 33}, "time": 32}, "20": {"q1": 0, "q3": 2, "q2": 90, "bb": {"h": 86, "startX": 463, "startY": 307, "w": 32}, "time": 43}, "21": {"q1": 0, "q3": 2, "q2": 90, "bb": {"h": 25, "startX": 147, "startY": 413, "w": 41}, "time": 29}, "22": {"q1": 0, "q3": 2, "q2": 90, "bb": {"h": -10, "startX": 248, "startY": 259, "w": 38}, "time": 20}, "23": {"q1": 0, "q3": 2, "q2": 80, "bb": {"h": 67, "startX": 436, "startY": 360, "w": 16}, "time": 47}, "24": {"q1": 0, "q3": 2, "q2": 80, "bb": {"h": 20, "startX": 456, "startY": 52, "w": 11}, "time": 24}, "demographic": {"major": "computer science", "estimation": "No", "gender": "Male", "age": "59", "nativeLanguage": "English", "job": "finance", "nativeSpeaker": "Yes", "employed": "Yes", "education": "4 year degree", "stayInUS": "Native (all my life)"}, "name": "ACCQN14OV2GG3"}, {"1": {"q1": 0, "q3": 2, "q2": 90, "bb": {"h": 198, "startX": 226, "startY": 303, "w": 202}, "time": 11}, "2": {"q1": 0, "q3": 2, "q2": 90, "bb": {"h": 159, "startX": 178, "startY": 329, "w": 198}, "time": 8}, "3": {"q1": 1, "q3": 1, "q2": 100, "bb": {"h": 143, "startX": 27, "startY": 160, "w": 132}, "time": 15}, "4": {"q1": 0, "q3": 2, "q2": 80, "bb": {"h": 88, "startX": 210, "startY": 151, "w": 162}, "time": 29}, "5": {"q1": 0, "q3": 2, "q2": 90, "bb": {"h": 154, "startX": 26, "startY": 294, "w": 172}, "time": 14}, "6": {"q1": 0, "q3": 2, "q2": 80, "bb": {"h": 123, "startX": 368, "startY": 237, "w": 122}, "time": 23}, "7": {"q1": 0, "q3": 1, "q2": 90, "bb": {"h": 145, "startX": 189, "startY": 166, "w": 156}, "time": 8}, "8": {"q1": 0, "q3": 1, "q2": 90, "bb": {"h": 174, "startX": 105, "startY": 226, "w": 140}, "time": 10}, "9": {"q1": 0, "q3": 2, "q2": 80, "bb": {"h": 110, "startX": 176, "startY": 224, "w": 127}, "time": 15}, "10": {"q1": 0, "q3": 2, "q2": 90, "bb": {"h": 135, "startX": 176, "startY": 217, "w": 181}, "time": 38}, "11": {"q1": 0, "q3": 2, "q2": 90, "bb": {"h": 173, "startX": 203, "startY": 187, "w": 149}, "time": 12}, "12": {"q1": 0, "q3": 2, "q2": 90, "bb": {"h": 102, "startX": 250, "startY": 309, "w": 174}, "time": 14}, "13": {"q1": 0, "q3": 2, "q2": 90, "bb": {"h": 155, "startX": 120, "startY": 241, "w": 140}, "time": 16}, "14": {"q1": 0, "q3": 2, "q2": 90, "bb": {"h": 130, "startX": 176, "startY": 15, "w": 179}, "time": 13}, "15": {"q1": 0, "q3": 2, "q2": 90, "bb": {"h": 148, "startX": 137, "startY": 130, "w": 182}, "time": 65}, "16": {"q1": 0, "q3": 2, "q2": 90, "bb": {"h": 122, "startX": 243, "startY": 103, "w": 101}, "time": 8}, "17": {"q1": 0, "q3": 2, "q2": 90, "bb": {"h": 161, "startX": 163, "startY": 206, "w": 173}, "time": 10}, "18": {"q1": 0, "q3": 2, "q2": 90, "bb": {"h": 102, "startX": 32, "startY": 399, "w": 106}, "time": 14}, "19": {"q1": 0, "q3": 1, "q2": 90, "bb": {"h": 112, "startX": 343, "startY": 201, "w": -79}, "time": 19}, "20": {"q1": 0, "q3": 2, "q2": 90, "bb": {"h": 163, "startX": 277, "startY": 312, "w": 137}, "time": 20}, "21": {"q1": 0, "q3": 3, "q2": 80, "bb": {"h": 137, "startX": 171, "startY": 237, "w": 139}, "time": 9}, "22": {"q1": 0, "q3": 2, "q2": 90, "bb": {"h": 178, "startX": 77, "startY": 121, "w": 154}, "time": 11}, "23": {"q1": 0, "q3": 2, "q2": 90, "bb": {"h": 155, "startX": 295, "startY": 216, "w": 132}, "time": 9}, "24": {"q1": 0, "q3": 1, "q2": 90, "bb": {"h": 138, "startX": 297, "startY": 262, "w": 143}, "time": 11}, "demographic": {"major": "science", "estimation": "No", "gender": "Female", "age": "25", "nativeLanguage": "english", "job": "manager", "nativeSpeaker": "Yes", "employed": "Yes", "education": "Master's", "stayInUS": "Native (all my life)"}, "name": "A17EFMUJ0TLV2C"}, {"1": {"q1": 0, "q3": 3, "q2": 90, "bb": {"h": 139, "startX": 56, "startY": 14, "w": 240}, "time": 12}, "2": {"q1": 0, "q3": 3, "q2": 100, "bb": {"h": 116, "startX": 187, "startY": 359, "w": 255}, "time": 20}, "3": {"q1": 1, "q3": 2, "q2": 100, "bb": {"h": 145, "startX": 38, "startY": 166, "w": 120}, "time": 16}, "4": {"q1": 1, "q3": 2, "q2": 100, "bb": {"h": 81, "startX": 68, "startY": 292, "w": 132}, "time": 11}, "5": {"q1": 0, "q3": 3, "q2": 100, "bb": {"h": 86, "startX": 187, "startY": 37, "w": 223}, "time": 38}, "6": {"q1": 0, "q3": 3, "q2": 100, "bb": {"h": 180, "startX": 43, "startY": 71, "w": 201}, "time": 13}, "7": {"q1": 0, "q3": 3, "q2": 100, "bb": {"h": 82, "startX": 271, "startY": 338, "w": 165}, "time": 17}, "8": {"q1": 0, "q3": 3, "q2": 100, "bb": {"h": -112, "startX": 211, "startY": 170, "w": -152}, "time": 12}, "9": {"q1": 0, "q3": 3, "q2": 100, "bb": {"h": 110, "startX": 267, "startY": 356, "w": 194}, "time": 11}, "10": {"q1": 1, "q3": 4, "q2": 70, "bb": {"h": 126, "startX": 171, "startY": 222, "w": 115}, "time": 16}, "11": {"q1": 0, "q3": 3, "q2": 100, "bb": {"h": 107, "startX": 12, "startY": 375, "w": 110}, "time": 20}, "12": {"q1": 0, "q3": 3, "q2": 100, "bb": {"h": 65, "startX": 6, "startY": 426, "w": 94}, "time": 22}, "13": {"q1": 0, "q3": 3, "q2": 100, "bb": {"h": 99, "startX": 414, "startY": 375, "w": 70}, "time": 18}, "14": {"q1": 0, "q3": 3, "q2": 100, "bb": {"h": 151, "startX": 347, "startY": 180, "w": 280}, "time": 16}, "15": {"q1": 0, "q3": 3, "q2": 90, "bb": {"h": 194, "startX": 289, "startY": 134, "w": 192}, "time": 14}, "16": {"q1": 0, "q3": 3, "q2": 100, "bb": {"h": 78, "startX": 130, "startY": 375, "w": 168}, "time": 19}, "17": {"q1": 0, "q3": 3, "q2": 90, "bb": {"h": 73, "startX": 384, "startY": 381, "w": 77}, "time": 11}, "18": {"q1": 0, "q3": 3, "q2": 100, "bb": {"h": 107, "startX": 284, "startY": 28, "w": 160}, "time": 15}, "19": {"q1": 0, "q3": 3, "q2": 100, "bb": {"h": -129, "startX": 106, "startY": 472, "w": -79}, "time": 15}, "20": {"q1": 0, "q3": 3, "q2": 90, "bb": {"h": 132, "startX": 251, "startY": 28, "w": 213}, "time": 12}, "21": {"q1": 0, "q3": 3, "q2": 100, "bb": {"h": -107, "startX": 79, "startY": 300, "w": -63}, "time": 26}, "22": {"q1": 0, "q3": 3, "q2": 100, "bb": {"h": 75, "startX": 251, "startY": 312, "w": 117}, "time": 17}, "23": {"q1": 0, "q3": 3, "q2": 100, "bb": {"h": 119, "startX": 241, "startY": 221, "w": 162}, "time": 11}, "24": {"q1": 0, "q3": 3, "q2": 100, "bb": {"h": 187, "startX": 53, "startY": 80, "w": 168}, "time": 13}, "demographic": {"major": "na", "estimation": "No", "specify": "na", "gender": "Female", "age": "25", "nativeLanguage": "English", "job": "Mid level Manager", "nativeSpeaker": "Yes", "employed": "Yes", "education": "Master's", "stayInUS": "Native (all my life)"}, "name": "A1ALX91R7G6ABQ"}, {"1": {"q1": 1, "q3": 3, "q2": 90, "bb": {"h": 141, "startX": 256, "startY": 160, "w": 78}, "time": 10}, "2": {"q1": 1, "q3": 3, "q2": 90, "bb": {"h": 134, "startX": 136, "startY": 108, "w": 338}, "time": 11}, "3": {"q1": 1, "q3": 3, "q2": 80, "bb": {"h": 191, "startX": 113, "startY": 199, "w": 113}, "time": 7}, "4": {"q1": 1, "q3": 3, "q2": 80, "bb": {"h": 221, "startX": 144, "startY": 116, "w": 149}, "time": 7}, "5": {"q1": 1, "q3": 4, "q2": 80, "bb": {"h": 184, "startX": 115, "startY": 5, "w": 164}, "time": 7}, "6": {"q1": 1, "q3": 3, "q2": 80, "bb": {"h": 140, "startX": 152, "startY": 40, "w": 168}, "time": 8}, "7": {"q1": 1, "q3": 3, "q2": 80, "bb": {"h": 105, "startX": 244, "startY": 69, "w": 53}, "time": 8}, "8": {"q1": 1, "q3": 3, "q2": 90, "bb": {"h": 152, "startX": 237, "startY": 264, "w": 81}, "time": 17}, "9": {"q1": 1, "q3": 3, "q2": 80, "bb": {"h": 128, "startX": 193, "startY": 68, "w": 111}, "time": 8}, "10": {"q1": 1, "q3": 3, "q2": 80, "bb": {"h": 112, "startX": 231, "startY": 225, "w": 93}, "time": 23}, "11": {"q1": 1, "q3": 3, "q2": 80, "bb": {"h": 75, "startX": 118, "startY": 119, "w": 203}, "time": 11}, "12": {"q1": 1, "q3": 3, "q2": 90, "bb": {"h": 138, "startX": 90, "startY": 242, "w": 109}, "time": 23}, "13": {"q1": 1, "q3": 3, "q2": 80, "bb": {"h": 81, "startX": 232, "startY": 330, "w": 72}, "time": 18}, "14": {"q1": 1, "q3": 3, "q2": 90, "bb": {"h": 91, "startX": 86, "startY": 62, "w": 156}, "time": 9}, "15": {"q1": 1, "q3": 3, "q2": 80, "bb": {"h": 157, "startX": 92, "startY": 37, "w": 178}, "time": 8}, "16": {"q1": 1, "q3": 3, "q2": 80, "bb": {"h": 70, "startX": 173, "startY": 139, "w": 115}, "time": 8}, "17": {"q1": 1, "q3": 3, "q2": 80, "bb": {"h": 373, "startX": 158, "startY": 127, "w": 251}, "time": 7}, "18": {"q1": 1, "q3": 4, "q2": 90, "bb": {"h": 222, "startX": 102, "startY": 114, "w": 94}, "time": 9}, "19": {"q1": 1, "q3": 3, "q2": 90, "bb": {"h": 45, "startX": 154, "startY": 336, "w": 66}, "time": 13}, "20": {"q1": 1, "q3": 3, "q2": 70, "bb": {"h": 117, "startX": 185, "startY": 267, "w": 88}, "time": 8}, "21": {"q1": 0, "q3": 3, "q2": 90, "bb": {"h": 74, "startX": 120, "startY": 165, "w": 208}, "time": 8}, "22": {"q1": 1, "q3": 3, "q2": 80, "bb": {"h": 94, "startX": 229, "startY": 236, "w": 52}, "time": 9}, "23": {"q1": 1, "q3": 3, "q2": 80, "bb": {"h": 97, "startX": 178, "startY": 180, "w": 48}, "time": 9}, "24": {"q1": 1, "q3": 4, "q2": 80, "bb": {"h": 85, "startX": 178, "startY": 107, "w": 142}, "time": 9}, "demographic": {"major": "physics", "estimation": "No", "gender": "Female", "age": "37", "nativeLanguage": "no", "job": "production", "nativeSpeaker": "Yes", "employed": "Yes", "education": "4 year degree", "stayInUS": "Greater than 5 years"}, "name": "AMQKASFUOOFAM"}, {"1": {"q1": 1, "q3": 2, "q2": 80, "bb": {"h": 278, "startX": 390, "startY": 414, "w": 217}, "time": 12}, "2": {"q1": 0, "q3": 3, "q2": 80, "bb": {"h": 278, "startX": 168, "startY": 65, "w": 193}, "time": 9}, "3": {"q1": 1, "q3": 3, "q2": 70, "bb": {"h": 226, "startX": 153, "startY": 96, "w": 188}, "time": 10}, "4": {"q1": 0, "q3": 3, "q2": 70, "bb": {"h": 62, "startX": 346, "startY": 361, "w": 90}, "time": 10}, "5": {"q1": 0, "q3": 3, "q2": 80, "bb": {"h": 282, "startX": 249, "startY": 168, "w": 174}, "time": 11}, "6": {"q1": 0, "q3": 2, "q2": 80, "bb": {"h": 0, "startX": 419, "startY": 312, "w": -3}, "time": 20}, "7": {"q1": 1, "q3": 3, "q2": 80, "bb": {"h": 221, "startX": 152, "startY": 129, "w": 209}, "time": 11}, "8": {"q1": 1, "q3": 2, "q2": 70, "bb": {"h": 187, "startX": 175, "startY": 71, "w": 177}, "time": 19}, "9": {"q1": 0, "q3": 2, "q2": 70, "bb": {"h": 236, "startX": 140, "startY": 51, "w": 223}, "time": 12}, "10": {"q1": 1, "q3": 2, "q2": 70, "bb": {"h": 118, "startX": 181, "startY": 35, "w": 137}, "time": 15}, "11": {"q1": 1, "q3": 3, "q2": 80, "bb": {"h": 223, "startX": 158, "startY": 66, "w": 195}, "time": 9}, "12": {"q1": 1, "q3": 3, "q2": 80, "bb": {"h": 175, "startX": 225, "startY": 241, "w": 187}, "time": 13}, "13": {"q1": 0, "q3": 3, "q2": 70, "bb": {"h": 199, "startX": 191, "startY": 203, "w": 265}, "time": 8}, "14": {"q1": 0, "q3": 3, "q2": 80, "bb": {"h": 92, "startX": 237, "startY": 300, "w": 114}, "time": 10}, "15": {"q1": 1, "q3": 3, "q2": 80, "bb": {"h": 296, "startX": 57, "startY": 49, "w": 164}, "time": 11}, "16": {"q1": 0, "q3": 3, "q2": 80, "bb": {"h": 196, "startX": 113, "startY": 246, "w": 275}, "time": 16}, "17": {"q1": 0, "q3": 3, "q2": 80, "bb": {"h": 331, "startX": 137, "startY": 158, "w": 283}, "time": 8}, "18": {"q1": 1, "q3": 3, "q2": 90, "bb": {"h": 147, "startX": 102, "startY": 199, "w": 155}, "time": 10}, "19": {"q1": 1, "q3": 3, "q2": 80, "bb": {"h": 278, "startX": 166, "startY": 84, "w": 153}, "time": 8}, "20": {"q1": 0, "q3": 3, "q2": 80, "bb": {"h": 266, "startX": 187, "startY": 105, "w": 139}, "time": 7}, "21": {"q1": 0, "q3": 3, "q2": 80, "bb": {"h": 275, "startX": 207, "startY": 164, "w": 250}, "time": 10}, "22": {"q1": 1, "q3": 4, "q2": 80, "bb": {"h": 259, "startX": 167, "startY": 126, "w": 188}, "time": 8}, "23": {"q1": 0, "q3": 2, "q2": 80, "bb": {"h": 159, "startX": 398, "startY": 43, "w": 130}, "time": 35}, "24": {"q1": 1, "q3": 3, "q2": 90, "bb": {"h": 119, "startX": 162, "startY": 205, "w": 161}, "time": 17}, "demographic": {"major": "health science", "estimation": "No", "gender": "Female", "age": "24", "nativeLanguage": "English", "job": "Manager", "nativeSpeaker": "Yes", "employed": "Yes", "education": "Master's", "stayInUS": "Native (all my life)"}, "name": "A3KV17CTC8086F"}, {"1": {"q1": 1, "q3": 3, "q2": 90, "bb": {"h": -144, "startX": 255, "startY": 497, "w": 131}, "time": 66}, "2": {"q1": 1, "q3": 2, "q2": 100, "bb": {"h": 139, "startX": 95, "startY": 80, "w": 112}, "time": 11}, "3": {"q1": 1, "q3": 2, "q2": 90, "bb": {"h": 124, "startX": 38, "startY": 159, "w": 154}, "time": 60}, "4": {"q1": 1, "q3": 2, "q2": 100, "bb": {"h": 124, "startX": 56, "startY": 263, "w": 172}, "time": 13}, "5": {"q1": 0, "q3": 2, "q2": 100, "bb": {"h": null, "startX": 281, "startY": 294, "w": null}, "time": 19}, "6": {"q1": 1, "q3": 2, "q2": 90, "bb": {"h": 135, "startX": 271, "startY": 311, "w": 154}, "time": 12}, "7": {"q1": 1, "q3": 2, "q2": 90, "bb": {"h": 130, "startX": 325, "startY": 244, "w": 151}, "time": 27}, "8": {"q1": 1, "q3": 2, "q2": 100, "bb": {"h": 133, "startX": 204, "startY": 131, "w": 142}, "time": 10}, "9": {"q1": 0, "q3": 2, "q2": 90, "bb": {"h": null, "startX": 214, "startY": 294, "w": null}, "time": 32}, "10": {"q1": 1, "q3": 2, "q2": 100, "bb": {"h": 125, "startX": 184, "startY": 214, "w": 115}, "time": 12}, "11": {"q1": 1, "q3": 2, "q2": 90, "bb": {"h": 135, "startX": 198, "startY": 225, "w": 148}, "time": 11}, "12": {"q1": 1, "q3": 2, "q2": 90, "bb": {"h": 209, "startX": 197, "startY": 184, "w": 127}, "time": 14}, "13": {"q1": 1, "q3": 2, "q2": 90, "bb": {"h": 88, "startX": 383, "startY": 409, "w": 118}, "time": 19}, "14": {"q1": 0, "q3": 2, "q2": 90, "bb": {"h": null, "startX": 229, "startY": 299, "w": null}, "time": 18}, "15": {"q1": 1, "q3": 2, "q2": 90, "bb": {"h": 108, "startX": 271, "startY": 145, "w": 93}, "time": 13}, "16": {"q1": 1, "q3": 2, "q2": 90, "bb": {"h": 147, "startX": 256, "startY": 267, "w": 102}, "time": 26}, "17": {"q1": 1, "q3": 2, "q2": 90, "bb": {"h": 155, "startX": 414, "startY": 148, "w": 86}, "time": 26}, "18": {"q1": 1, "q3": 2, "q2": 100, "bb": {"h": 155, "startX": 191, "startY": 320, "w": 109}, "time": 16}, "19": {"q1": 1, "q3": 2, "q2": 100, "bb": {"h": 113, "startX": 110, "startY": 50, "w": 123}, "time": 20}, "20": {"q1": 1, "q3": 2, "q2": 90, "bb": {"h": 106, "startX": 115, "startY": 140, "w": 93}, "time": 38}, "21": {"q1": 1, "q3": 2, "q2": 100, "bb": {"h": 109, "startX": 294, "startY": 213, "w": 120}, "time": 16}, "22": {"q1": 0, "q3": 2, "q2": 100, "bb": {"h": null, "startX": 296, "startY": 201, "w": null}, "time": 18}, "23": {"q1": 0, "q3": 2, "q2": 90, "bb": {"h": null, "startX": 359, "startY": 165, "w": null}, "time": 35}, "24": {"q1": 1, "q3": 2, "q2": 90, "bb": {"h": 138, "startX": 295, "startY": 261, "w": 153}, "time": 9}, "demographic": {"major": "maths", "estimation": "No", "gender": "Male", "age": "35", "nativeLanguage": "english", "job": "marketing", "nativeSpeaker": "Yes", "employed": "Yes", "education": "4 year degree", "stayInUS": "Native (all my life)"}, "name": "AWKNHPWRWKQDG"}, {"1": {"q1": 0, "q3": 1, "q2": 90, "bb": {"h": 22, "startX": 237, "startY": 250, "w": 47}, "time": 30}, "2": {"q1": 0, "q3": 1, "q2": 90, "bb": {"h": 26, "startX": 178, "startY": 156, "w": 41}, "time": 43}, "3": {"q1": 0, "q3": 1, "q2": 90, "bb": {"h": 64, "startX": 301, "startY": 92, "w": 29}, "time": 42}, "4": {"q1": 1, "q3": 1, "q2": 90, "bb": {"h": 90, "startX": 67, "startY": 280, "w": 147}, "time": 19}, "5": {"q1": 0, "q3": 1, "q2": 90, "bb": {"h": 47, "startX": 212, "startY": 171, "w": 41}, "time": 31}, "6": {"q1": 0, "q3": 1, "q2": 90, "bb": {"h": 45, "startX": 194, "startY": 176, "w": 45}, "time": 26}, "7": {"q1": 1, "q3": 1, "q2": 90, "bb": {"h": 141, "startX": 65, "startY": 1, "w": 180}, "time": 41}, "8": {"q1": 0, "q3": 1, "q2": 90, "bb": {"h": 45, "startX": 161, "startY": 378, "w": 51}, "time": 28}, "9": {"q1": 0, "q3": 1, "q2": 90, "bb": {"h": 55, "startX": 174, "startY": 234, "w": 45}, "time": 24}, "10": {"q1": 0, "q3": 1, "q2": 90, "bb": {"h": 30, "startX": 186, "startY": 199, "w": 42}, "time": 32}, "11": {"q1": 0, "q3": 1, "q2": 90, "bb": {"h": 65, "startX": 251, "startY": 321, "w": 68}, "time": 28}, "12": {"q1": 0, "q3": 1, "q2": 90, "bb": {"h": 52, "startX": 228, "startY": 320, "w": 35}, "time": 25}, "13": {"q1": 0, "q3": 1, "q2": 90, "bb": {"h": 25, "startX": 118, "startY": 267, "w": 45}, "time": 34}, "14": {"q1": 0, "q3": 1, "q2": 90, "bb": {"h": 68, "startX": 195, "startY": 181, "w": 56}, "time": 32}, "15": {"q1": 0, "q3": 1, "q2": 90, "bb": {"h": 79, "startX": 228, "startY": 267, "w": 66}, "time": 38}, "16": {"q1": 0, "q3": 1, "q2": 90, "bb": {"h": 52, "startX": 268, "startY": 204, "w": 77}, "time": 29}, "17": {"q1": 0, "q3": 1, "q2": 90, "bb": {"h": 27, "startX": 192, "startY": 328, "w": 45}, "time": 35}, "18": {"q1": 0, "q3": 1, "q2": 90, "bb": {"h": 34, "startX": 288, "startY": 283, "w": 42}, "time": 33}, "19": {"q1": 0, "q3": 1, "q2": 90, "bb": {"h": 43, "startX": 270, "startY": 334, "w": 41}, "time": 20}, "20": {"q1": 0, "q3": 1, "q2": 90, "bb": {"h": 27, "startX": 192, "startY": 328, "w": 45}, "time": 36}, "21": {"q1": 0, "q3": 1, "q2": 90, "bb": {"h": 59, "startX": 243, "startY": 210, "w": 58}, "time": 43}, "22": {"q1": 0, "q3": 1, "q2": 90, "bb": {"h": 36, "startX": 202, "startY": 250, "w": 44}, "time": 42}, "23": {"q1": 0, "q3": 1, "q2": 90, "bb": {"h": 43, "startX": 48, "startY": 278, "w": 73}, "time": 33}, "24": {"q1": 0, "q3": 1, "q2": 90, "bb": {"h": 40, "startX": 144, "startY": 190, "w": 33}, "time": 38}, "demographic": {"major": "Yale university", "estimation": "No", "gender": "Female", "nativeLanguage": "English", "job": "Manager", "nativeSpeaker": "Yes", "employed": "Yes", "education": "Master's", "stayInUS": "Greater than 5 years"}, "name": "AIHMHBXQN27E5"}, {"1": {"q1": 0, "q3": 3, "q2": 70, "bb": {"h": 151, "startX": 127, "startY": 78, "w": 50}, "time": 8}, "2": {"q1": 0, "q3": 4, "q2": 80, "bb": {"h": 175, "startX": 164, "startY": 60, "w": 45}, "time": 10}, "3": {"q1": 0, "q3": 4, "q2": 90, "bb": {"h": 171, "startX": 143, "startY": 114, "w": 79}, "time": 10}, "4": {"q1": 0, "q3": 4, "q2": 90, "bb": {"h": 173, "startX": 143, "startY": 179, "w": 94}, "time": 9}, "5": {"q1": 0, "q3": 3, "q2": 80, "bb": {"h": 156, "startX": 157, "startY": 114, "w": 72}, "time": 9}, "6": {"q1": 0, "q3": 3, "q2": 90, "bb": {"h": 111, "startX": 139, "startY": 369, "w": 99}, "time": 13}, "7": {"q1": 0, "q3": 4, "q2": 80, "bb": {"h": 144, "startX": 135, "startY": 93, "w": 72}, "time": 13}, "8": {"q1": 0, "q3": 3, "q2": 90, "bb": {"h": 194, "startX": 68, "startY": 173, "w": 90}, "time": 11}, "9": {"q1": 1, "q3": 3, "q2": 90, "bb": {"h": 0, "startX": 496, "startY": 487, "w": 1}, "time": 40}, "10": {"q1": 1, "q3": 4, "q2": 80, "bb": {"h": 118, "startX": 167, "startY": 145, "w": 65}, "time": 11}, "11": {"q1": 0, "q3": 3, "q2": 70, "bb": {"h": 123, "startX": 107, "startY": 97, "w": 36}, "time": 8}, "12": {"q1": 0, "q3": 3, "q2": 90, "bb": {"h": 197, "startX": 127, "startY": 208, "w": 131}, "time": 8}, "13": {"q1": 0, "q3": 4, "q2": 80, "bb": {"h": 135, "startX": 165, "startY": 357, "w": 77}, "time": 12}, "14": {"q1": 0, "q3": 4, "q2": 80, "bb": {"h": 109, "startX": 149, "startY": 133, "w": 105}, "time": 10}, "15": {"q1": 0, "q3": 3, "q2": 80, "bb": {"h": 210, "startX": 89, "startY": 122, "w": 195}, "time": 10}, "16": {"q1": 1, "q3": 3, "q2": 90, "bb": {"h": 118, "startX": 109, "startY": 90, "w": 78}, "time": 9}, "17": {"q1": 0, "q3": 4, "q2": 80, "bb": {"h": 182, "startX": 134, "startY": 8, "w": 93}, "time": 9}, "18": {"q1": 0, "q3": 3, "q2": 80, "bb": {"h": 199, "startX": 105, "startY": 53, "w": 133}, "time": 12}, "19": {"q1": 0, "q3": 3, "q2": 80, "bb": {"h": 165, "startX": 79, "startY": 78, "w": 65}, "time": 11}, "20": {"q1": 0, "q3": 4, "q2": 90, "bb": {"h": 89, "startX": 120, "startY": 355, "w": 98}, "time": 17}, "21": {"q1": 0, "q3": 3, "q2": 50, "bb": {"h": 231, "startX": 192, "startY": 148, "w": 112}, "time": 9}, "22": {"q1": 0, "q3": 3, "q2": 90, "bb": {"h": 147, "startX": 241, "startY": 107, "w": 71}, "time": 21}, "23": {"q1": 0, "q3": 3, "q2": 80, "bb": {"h": 113, "startX": 129, "startY": 272, "w": 69}, "time": 9}, "24": {"q1": 0, "q3": 3, "q2": 80, "bb": {"h": 224, "startX": 154, "startY": 118, "w": 70}, "time": 8}, "demographic": {"major": "Bachelor", "estimation": "No", "gender": "Male", "age": "30", "job": "IT", "nativeSpeaker": "Yes", "employed": "Yes", "education": "4 year degree", "stayInUS": "Native (all my life)"}, "name": "A3KSXBML8G1454"}, {"1": {"q1": 0, "q3": 4, "q2": 70, "bb": {"h": 41, "startX": 11, "startY": 323, "w": 22}, "time": 50}, "2": {"q1": 1, "q3": 2, "q2": 70, "bb": {"h": 90, "startX": 5, "startY": 195, "w": 85}, "time": 42}, "3": {"q1": 1, "q3": 2, "q2": 80, "bb": {"h": 62, "startX": 102, "startY": 217, "w": -70}, "time": 43}, "4": {"q1": 1, "q3": 1, "q2": 100, "bb": {"h": 70, "startX": 87, "startY": 289, "w": 127}, "time": 19}, "5": {"q1": 0, "q3": 1, "q2": 80, "bb": {"h": null, "startX": 119, "startY": 372, "w": null}, "time": 31}, "6": {"q1": 1, "q3": 4, "q2": 30, "bb": {"h": -25, "startX": 332, "startY": 151, "w": -196}, "time": 58}, "7": {"q1": 1, "q3": 3, "q2": 60, "bb": {"h": 61, "startX": 392, "startY": 325, "w": 75}, "time": 21}, "8": {"q1": 1, "q3": 3, "q2": 80, "bb": {"h": 65, "startX": 83, "startY": 7, "w": 37}, "time": 51}, "9": {"q1": 1, "q3": 4, "q2": 60, "bb": {"h": 138, "startX": 454, "startY": 360, "w": 45}, "time": 33}, "10": {"q1": 1, "q3": 3, "q2": 40, "bb": {"h": 79, "startX": 411, "startY": 178, "w": 81}, "time": 44}, "11": {"q1": 1, "q3": 3, "q2": 70, "bb": {"h": 43, "startX": 171, "startY": 331, "w": 75}, "time": 25}, "12": {"q1": 1, "q3": 2, "q2": 60, "bb": {"h": 56, "startX": 369, "startY": 20, "w": 117}, "time": 34}, "13": {"q1": 0, "q3": 3, "q2": 70, "bb": {"h": 60, "startX": 107, "startY": 182, "w": 49}, "time": 60}, "14": {"q1": 1, "q3": 2, "q2": 80, "bb": {"h": 48, "startX": 37, "startY": 448, "w": 109}, "time": 51}, "15": {"q1": 1, "q3": 4, "q2": 80, "bb": {"h": 68, "startX": 1, "startY": 214, "w": 62}, "time": 33}, "16": {"q1": 0, "q3": 4, "q2": 70, "bb": {"h": 18, "startX": 190, "startY": 367, "w": 52}, "time": 37}, "17": {"q1": 0, "q3": 4, "q2": 70, "bb": {"h": 64, "startX": 227, "startY": 103, "w": 81}, "time": 42}, "18": {"q1": 1, "q3": 4, "q2": 30, "bb": {"h": 48, "startX": 140, "startY": 185, "w": 28}, "time": 43}, "19": {"q1": 1, "q3": 3, "q2": 80, "bb": {"h": 105, "startX": 461, "startY": 172, "w": 38}, "time": 43}, "20": {"q1": 0, "q3": 3, "q2": 60, "bb": {"h": 49, "startX": 426, "startY": 399, "w": 38}, "time": 20}, "21": {"q1": 0, "q3": 3, "q2": 70, "bb": {"h": 65, "startX": 47, "startY": 236, "w": 150}, "time": 33}, "22": {"q1": 0, "q3": 2, "q2": 40, "bb": {"h": 323, "startX": 443, "startY": 22, "w": 50}, "time": 28}, "23": {"q1": 1, "q3": 3, "q2": 80, "bb": {"h": 56, "startX": 156, "startY": 445, "w": 100}, "time": 30}, "24": {"q1": 0, "q3": 2, "q2": 70, "bb": {"h": 66, "startX": 36, "startY": 135, "w": 58}, "time": 36}, "demographic": {"major": "Computer Science", "estimation": "No", "specify": "NO", "gender": "Female", "age": "48", "nativeLanguage": "English", "job": "Manager", "nativeSpeaker": "Yes", "employed": "Yes", "education": "Master's", "stayInUS": "Native (all my life)"}, "name": "A106M0HTZXY7JK"}, {"1": {"q1": 0, "q3": 2, "q2": 40, "bb": {"h": 182, "startX": 111, "startY": 252, "w": 295}, "time": 33}, "2": {"q1": 0, "q3": 2, "q2": 40, "bb": {"h": 206, "startX": 56, "startY": 240, "w": 387}, "time": 10}, "3": {"q1": 0, "q3": 3, "q2": 30, "bb": {"h": 195, "startX": 64, "startY": 241, "w": 352}, "time": 14}, "4": {"q1": 1, "q3": 2, "q2": 90, "bb": {"h": 133, "startX": 62, "startY": 275, "w": 192}, "time": 16}, "5": {"q1": 0, "q3": 3, "q2": 40, "bb": {"h": 162, "startX": 127, "startY": 299, "w": 312}, "time": 12}, "6": {"q1": 0, "q3": 2, "q2": 40, "bb": {"h": 206, "startX": 87, "startY": 216, "w": 294}, "time": 15}, "7": {"q1": 1, "q3": 2, "q2": 80, "bb": {"h": 160, "startX": 90, "startY": 229, "w": 259}, "time": 17}, "8": {"q1": 0, "q3": 2, "q2": 40, "bb": {"h": 172, "startX": 101, "startY": 259, "w": 298}, "time": 16}, "9": {"q1": 0, "q3": 4, "q2": 40, "bb": {"h": 178, "startX": 82, "startY": 224, "w": 290}, "time": 13}, "10": {"q1": 0, "q3": 2, "q2": 40, "bb": {"h": 150, "startX": 78, "startY": 281, "w": 288}, "time": 9}, "11": {"q1": 0, "q3": 3, "q2": 40, "bb": {"h": 220, "startX": 81, "startY": 236, "w": 354}, "time": 25}, "12": {"q1": 0, "q3": 2, "q2": 30, "bb": {"h": 232, "startX": 109, "startY": 238, "w": 296}, "time": 14}, "13": {"q1": 1, "q3": 2, "q2": 70, "bb": {"h": 191, "startX": 91, "startY": 64, "w": 316}, "time": 19}, "14": {"q1": 0, "q3": 3, "q2": 40, "bb": {"h": 197, "startX": 84, "startY": 218, "w": 325}, "time": 19}, "15": {"q1": 0, "q3": 2, "q2": 40, "bb": {"h": 155, "startX": 95, "startY": 249, "w": 329}, "time": 14}, "16": {"q1": 0, "q3": 2, "q2": 30, "bb": {"h": 130, "startX": 97, "startY": 313, "w": 289}, "time": 15}, "17": {"q1": 0, "q3": 3, "q2": 30, "bb": {"h": 149, "startX": 103, "startY": 281, "w": 261}, "time": 11}, "18": {"q1": 0, "q3": 3, "q2": 60, "bb": {"h": 203, "startX": 82, "startY": 261, "w": 357}, "time": 11}, "19": {"q1": 0, "q3": 2, "q2": 30, "bb": {"h": 229, "startX": 85, "startY": 189, "w": 316}, "time": 20}, "20": {"q1": 0, "q3": 3, "q2": 40, "bb": {"h": 177, "startX": 59, "startY": 258, "w": 368}, "time": 14}, "21": {"q1": 0, "q3": 2, "q2": 40, "bb": {"h": 164, "startX": 99, "startY": 269, "w": 331}, "time": 10}, "22": {"q1": 0, "q3": 2, "q2": 30, "bb": {"h": 140, "startX": 78, "startY": 281, "w": 309}, "time": 17}, "23": {"q1": 0, "q3": 2, "q2": 40, "bb": {"h": 162, "startX": 59, "startY": 261, "w": 388}, "time": 11}, "24": {"q1": 0, "q3": 2, "q2": 40, "bb": {"h": 216, "startX": 75, "startY": 228, "w": 357}, "time": 11}, "demographic": {"major": "computer science", "estimation": "No", "gender": "Female", "age": "24", "nativeLanguage": "english", "job": "manager", "nativeSpeaker": "Yes", "education": "Master's", "stayInUS": "Native (all my life)"}, "name": "A1XQLV2N8FHYKW"}, {"1": {"q1": 0, "q3": 4, "q2": 90, "bb": {"h": -225, "startX": 308, "startY": 235, "w": -286}, "time": 22}, "2": {"q1": 0, "q3": 3, "q2": 90, "bb": {"h": 225, "startX": 41, "startY": 61, "w": 284}, "time": 25}, "3": {"q1": 1, "q3": 1, "q2": 100, "bb": {"h": 137, "startX": 35, "startY": 154, "w": 118}, "time": 11}, "4": {"q1": 1, "q3": 1, "q2": 100, "bb": {"h": 91, "startX": 73, "startY": 281, "w": 147}, "time": 12}, "5": {"q1": 0, "q3": 4, "q2": 60, "bb": {"h": 342, "startX": 156, "startY": 36, "w": 344}, "time": 60}, "6": {"q1": 1, "q3": 4, "q2": 30, "bb": {"h": 100, "startX": 402, "startY": 46, "w": 96}, "time": 60}, "7": {"q1": 0, "q3": 4, "q2": 70, "bb": {"h": 346, "startX": 291, "startY": 150, "w": 206}, "time": 23}, "8": {"q1": 0, "q3": 2, "q2": 80, "bb": {"h": -242, "startX": 125, "startY": 332, "w": -112}, "time": 20}, "9": {"q1": 0, "q3": 3, "q2": 70, "bb": {"h": 318, "startX": 345, "startY": 137, "w": 143}, "time": 49}, "10": {"q1": 0, "q3": 3, "q2": 90, "bb": {"h": 295, "startX": 238, "startY": 195, "w": -216}, "time": 19}, "11": {"q1": 0, "q3": 4, "q2": 70, "bb": {"h": 239, "startX": 95, "startY": 259, "w": 385}, "time": 25}, "12": {"q1": 0, "q3": 4, "q2": 80, "bb": {"h": 316, "startX": 224, "startY": 176, "w": 266}, "time": 21}, "13": {"q1": 0, "q3": 3, "q2": 80, "bb": {"h": 226, "startX": 348, "startY": 258, "w": -301}, "time": 26}, "14": {"q1": 0, "q3": 3, "q2": 80, "bb": {"h": 215, "startX": 367, "startY": 261, "w": -215}, "time": 29}, "15": {"q1": 0, "q3": 3, "q2": 80, "bb": {"h": -337, "startX": 13, "startY": 474, "w": 224}, "time": 32}, "16": {"q1": 0, "q3": 3, "q2": 90, "bb": {"h": 264, "startX": 63, "startY": 136, "w": 205}, "time": 16}, "17": {"q1": 0, "q3": 4, "q2": 70, "bb": {"h": 247, "startX": 199, "startY": 99, "w": 289}, "time": 52}, "18": {"q1": 0, "q3": 2, "q2": 90, "bb": {"h": 280, "startX": 321, "startY": 100, "w": -264}, "time": 19}, "19": {"q1": 0, "q3": 3, "q2": 80, "bb": {"h": 187, "startX": 287, "startY": 27, "w": 171}, "time": 22}, "20": {"q1": 0, "q3": 4, "q2": 60, "bb": {"h": -198, "startX": 236, "startY": 202, "w": 262}, "time": 54}, "21": {"q1": 0, "q3": 4, "q2": 60, "bb": {"h": -311, "startX": 21, "startY": 315, "w": 305}, "time": 45}, "22": {"q1": 0, "q3": 4, "q2": 80, "bb": {"h": -164, "startX": 60, "startY": 173, "w": 373}, "time": 22}, "23": {"q1": 0, "q3": 3, "q2": 80, "bb": {"h": -333, "startX": 287, "startY": 365, "w": -271}, "time": 33}, "24": {"q1": 0, "q3": 3, "q2": 80, "bb": {"h": -189, "startX": 16, "startY": 7, "w": -172}, "time": 47}, "demographic": {"estimation": "No", "gender": "Male", "age": "35", "job": "audio engineer", "nativeSpeaker": "Yes", "employed": "Yes", "education": "High School/GED", "stayInUS": "Native (all my life)"}, "name": "A2NA6X1SON3KFH"}, {"1": {"q1": 1, "q3": 3, "q2": 50, "bb": {"h": -165, "startX": 191, "startY": 479, "w": 254}, "time": 26}, "2": {"q1": 1, "q3": 3, "q2": 50, "bb": {"h": -358, "startX": 72, "startY": 393, "w": 380}, "time": 15}, "3": {"q1": 1, "q3": 2, "q2": 90, "bb": {"h": -187, "startX": 23, "startY": 357, "w": 190}, "time": 16}, "4": {"q1": 1, "q3": 1, "q2": 90, "bb": {"h": -177, "startX": 54, "startY": 413, "w": 227}, "time": 15}, "5": {"q1": 1, "q3": 3, "q2": 50, "bb": {"h": -96, "startX": 262, "startY": 498, "w": 213}, "time": 37}, "6": {"q1": 1, "q3": 3, "q2": 30, "bb": {"h": -200, "startX": 344, "startY": 218, "w": 155}, "time": 17}, "7": {"q1": 1, "q3": 3, "q2": 50, "bb": {"h": -429, "startX": 381, "startY": 430, "w": -379}, "time": 20}, "8": {"q1": 1, "q3": 2, "q2": 50, "bb": {"h": -195, "startX": 318, "startY": 492, "w": 179}, "time": 21}, "9": {"q1": 1, "q3": 2, "q2": 60, "bb": {"h": -229, "startX": 15, "startY": 298, "w": 384}, "time": 24}, "10": {"q1": 1, "q3": 3, "q2": 50, "bb": {"h": -329, "startX": 80, "startY": 338, "w": 345}, "time": 23}, "11": {"q1": 1, "q3": 3, "q2": 20, "bb": {"h": -156, "startX": 314, "startY": 168, "w": 185}, "time": 49}, "12": {"q1": 1, "q3": 3, "q2": 50, "bb": {"h": -332, "startX": 116, "startY": 465, "w": 383}, "time": 35}, "13": {"q1": 1, "q3": 2, "q2": 80, "bb": {"h": -471, "startX": 70, "startY": 497, "w": 362}, "time": 23}, "14": {"q1": 1, "q3": 3, "q2": 30, "bb": {"h": -433, "startX": -2, "startY": 469, "w": 503}, "time": 25}, "15": {"q1": 1, "q3": 3, "q2": 50, "bb": {"h": -373, "startX": 16, "startY": 441, "w": 440}, "time": 18}, "16": {"q1": 1, "q3": 4, "q2": 20, "bb": {"h": -246, "startX": 69, "startY": 277, "w": 428}, "time": 31}, "17": {"q1": 1, "q3": 3, "q2": 50, "bb": {"h": -322, "startX": 12, "startY": 350, "w": 431}, "time": 39}, "18": {"q1": 1, "q3": 2, "q2": 70, "bb": {"h": -204, "startX": 260, "startY": 204, "w": 155}, "time": 16}, "19": {"q1": 1, "q3": 2, "q2": 60, "bb": {"h": -212, "startX": 222, "startY": 252, "w": 276}, "time": 17}, "20": {"q1": 1, "q3": 3, "q2": 40, "bb": {"h": -267, "startX": 21, "startY": 342, "w": 406}, "time": 26}, "21": {"q1": 1, "q3": 3, "q2": 50, "bb": {"h": -232, "startX": 205, "startY": 481, "w": 295}, "time": 23}, "22": {"q1": 1, "q3": 2, "q2": 50, "bb": {"h": -209, "startX": 62, "startY": 400, "w": 293}, "time": 14}, "23": {"q1": 1, "q3": 3, "q2": 60, "bb": {"h": -338, "startX": 34, "startY": 374, "w": 461}, "time": 35}, "24": {"q1": 1, "q3": 3, "q2": 40, "bb": {"h": -234, "startX": 17, "startY": 240, "w": 259}, "time": 18}, "demographic": {"major": "master degree", "estimation": "No", "gender": "Male", "age": "32", "nativeLanguage": "english", "job": "manager", "nativeSpeaker": "Yes", "employed": "Yes", "education": "Master's", "stayInUS": "Native (all my life)"}, "name": "A1S54RQW9FDK0X"}, {"1": {"q1": 1, "q3": 3, "q2": 90, "bb": {"h": 135, "startX": 248, "startY": 272, "w": 94}, "time": 15}, "2": {"q1": 1, "q3": 3, "q2": 70, "bb": {"h": 47, "startX": 108, "startY": 147, "w": 98}, "time": 16}, "3": {"q1": 1, "q3": 1, "q2": 80, "bb": {"h": 108, "startX": 47, "startY": 177, "w": 107}, "time": 17}, "4": {"q1": 1, "q3": 2, "q2": 100, "bb": {"h": 86, "startX": 93, "startY": 272, "w": 104}, "time": 10}, "5": {"q1": 0, "q3": 3, "q2": 80, "bb": {"h": 75, "startX": 307, "startY": 268, "w": 94}, "time": 11}, "6": {"q1": 1, "q3": 3, "q2": 80, "bb": {"h": 98, "startX": 277, "startY": 335, "w": 113}, "time": 10}, "7": {"q1": 1, "q3": 2, "q2": 80, "bb": {"h": 84, "startX": 421, "startY": 69, "w": 77}, "time": 12}, "8": {"q1": 1, "q3": 4, "q2": 70, "bb": {"h": 95, "startX": 332, "startY": 65, "w": 96}, "time": 12}, "9": {"q1": 0, "q3": 2, "q2": 80, "bb": {"h": 108, "startX": 358, "startY": 350, "w": 104}, "time": 9}, "10": {"q1": 0, "q3": 1, "q2": 80, "bb": {"h": 108, "startX": 9, "startY": 157, "w": 68}, "time": 14}, "11": {"q1": 1, "q3": 4, "q2": 60, "bb": {"h": 56, "startX": 382, "startY": 477, "w": 243}, "time": 17}, "12": {"q1": 0, "q3": 4, "q2": 30, "bb": {"h": 85, "startX": 382, "startY": 398, "w": 80}, "time": 12}, "13": {"q1": 1, "q3": 3, "q2": 10, "bb": {"h": 51, "startX": 47, "startY": 374, "w": 96}, "time": 15}, "14": {"q1": 0, "q3": 3, "q2": 90, "bb": {"h": 70, "startX": 373, "startY": 155, "w": 106}, "time": 18}, "15": {"q1": 1, "q3": 3, "q2": 70, "bb": {"h": 95, "startX": 42, "startY": 1, "w": 74}, "time": 29}, "16": {"q1": 0, "q3": 2, "q2": 30, "bb": {"h": 91, "startX": 271, "startY": 32, "w": 81}, "time": 11}, "17": {"q1": 0, "q3": 2, "q2": 60, "bb": {"h": 107, "startX": 373, "startY": 292, "w": 87}, "time": 22}, "18": {"q1": 1, "q3": 2, "q2": 80, "bb": {"h": 182, "startX": 433, "startY": 258, "w": 60}, "time": 18}, "19": {"q1": 0, "q3": 1, "q2": 60, "bb": {"h": 133, "startX": 92, "startY": 302, "w": 84}, "time": 35}, "20": {"q1": 1, "q3": 3, "q2": 80, "bb": {"h": 114, "startX": 2, "startY": 301, "w": 56}, "time": 19}, "21": {"q1": 0, "q3": 2, "q2": 90, "bb": {"h": 69, "startX": 116, "startY": 2, "w": 39}, "time": 14}, "22": {"q1": 0, "q3": 2, "q2": 70, "bb": {"h": 98, "startX": 227, "startY": 25, "w": 132}, "time": 16}, "23": {"q1": 1, "q3": 3, "q2": 70, "bb": {"h": 55, "startX": 89, "startY": 445, "w": 134}, "time": 12}, "24": {"q1": 0, "q3": 2, "q2": 60, "bb": {"h": 117, "startX": 72, "startY": 169, "w": 62}, "time": 14}, "demographic": {"major": "Computer science ", "estimation": "No", "gender": "Female", "age": "25", "nativeLanguage": "English", "job": "software developer ", "nativeSpeaker": "Yes", "employed": "Yes", "education": "4 year degree", "stayInUS": "Greater than 5 years"}, "name": "A18KLDM615KKX1"}, {"1": {"q1": 0, "q3": 4, "q2": 30, "bb": {"h": 54, "startX": 336, "startY": 194, "w": 35}, "time": 19}, "2": {"q1": 0, "q3": 4, "q2": 30, "bb": {"h": 72, "startX": 66, "startY": 197, "w": 155}, "time": 11}, "3": {"q1": 1, "q3": 2, "q2": 90, "bb": {"h": 139, "startX": 53, "startY": 159, "w": 104}, "time": 16}, "4": {"q1": 0, "q3": 4, "q2": 40, "bb": {"h": 59, "startX": 326, "startY": 10, "w": 164}, "time": 13}, "5": {"q1": 0, "q3": 4, "q2": 50, "bb": {"h": 92, "startX": 56, "startY": 333, "w": 129}, "time": 10}, "6": {"q1": 0, "q3": 4, "q2": 40, "bb": {"h": 81, "startX": 356, "startY": 7, "w": 134}, "time": 14}, "7": {"q1": 0, "q3": 4, "q2": 40, "bb": {"h": 97, "startX": 9, "startY": 26, "w": 29}, "time": 18}, "8": {"q1": 0, "q3": 4, "q2": 40, "bb": {"h": 118, "startX": 58, "startY": 191, "w": 34}, "time": 12}, "9": {"q1": 0, "q3": 4, "q2": 30, "bb": {"h": 99, "startX": 252, "startY": 368, "w": 206}, "time": 13}, "10": {"q1": 0, "q3": 4, "q2": 40, "bb": {"h": 36, "startX": 67, "startY": 279, "w": 82}, "time": 11}, "11": {"q1": 0, "q3": 3, "q2": 50, "bb": {"h": 163, "startX": 223, "startY": 200, "w": 117}, "time": 11}, "12": {"q1": 0, "q3": 4, "q2": 40, "bb": {"h": 128, "startX": 367, "startY": 52, "w": 82}, "time": 11}, "13": {"q1": 0, "q3": 4, "q2": 30, "bb": {"h": 77, "startX": 81, "startY": 83, "w": 135}, "time": 17}, "14": {"q1": 0, "q3": 4, "q2": 20, "bb": {"h": 36, "startX": 71, "startY": 19, "w": 111}, "time": 19}, "15": {"q1": 0, "q3": 4, "q2": 40, "bb": {"h": 102, "startX": 24, "startY": 191, "w": 42}, "time": 15}, "16": {"q1": 0, "q3": 4, "q2": 30, "bb": {"h": 58, "startX": 340, "startY": 2, "w": 138}, "time": 15}, "17": {"q1": 0, "q3": 4, "q2": 30, "bb": {"h": 115, "startX": 404, "startY": 198, "w": 62}, "time": 22}, "18": {"q1": 0, "q3": 3, "q2": 40, "bb": {"h": 112, "startX": 327, "startY": 12, "w": 108}, "time": 13}, "19": {"q1": 0, "q3": 4, "q2": 40, "bb": {"h": 118, "startX": 221, "startY": 183, "w": 98}, "time": 17}, "20": {"q1": 0, "q3": 4, "q2": 40, "bb": {"h": 77, "startX": 88, "startY": 96, "w": 100}, "time": 9}, "21": {"q1": 0, "q3": 4, "q2": 30, "bb": {"h": 85, "startX": 358, "startY": 57, "w": 34}, "time": 17}, "22": {"q1": 0, "q3": 3, "q2": 40, "bb": {"h": 96, "startX": 106, "startY": 233, "w": 129}, "time": 14}, "23": {"q1": 0, "q3": 4, "q2": 20, "bb": {"h": 96, "startX": 110, "startY": 68, "w": 90}, "time": 16}, "24": {"q1": 0, "q3": 4, "q2": 50, "bb": {"h": 142, "startX": 108, "startY": 6, "w": 86}, "time": 15}, "demographic": {"major": "Computer science", "estimation": "No", "gender": "Male", "age": "25", "job": "Software Developer", "nativeSpeaker": "Yes", "employed": "Yes", "education": "4 year degree", "stayInUS": "Greater than 5 years"}, "name": "A1I4I059H11BQP"}]